Workbook

Sheet Balance Sheet
B1: Balance Sheet ( All Amount in ₹ CR, Unless otherwise stated)
B3: Assets | C3: FY18 | D3: FY19 | E3: FY20 | F3: FY21 | G3: FY22 | H3: FY23 | I3: FY24 | J3: FY25E | K3: FY26E | L3: FY27E | M3: FY28E | N3: FY29E
B4: Non-current assets
A5: Capex | B5: Property, plant and equipment | C5: 264 | D5: 214 | E5: 14790 | F5: 14178 | G5: 12826 | H5: 26803 | I5: 26798 | J5: =Schedules_Populated!J71 -> 28150.664 | K5: =Schedules_Populated!K71 -> 30751.19 | L5: =Schedules_Populated!L71 -> 32972.031 | M5: =Schedules_Populated!M71 -> 35918.426 | N5: =Schedules_Populated!N71 -> 39023.19
B6: Capital work in progress | C6: 14 | D6: 0 | E6: 1344 | F6: 1199 | G6: 2646 | H6: 4054 | I6: 7504 | J6: =Assumptions!J22 -> 4736.7 | K6: =Assumptions!K22 -> 4935.78 | L6: =Assumptions!L22 -> 4815.722 | M6: =Assumptions!M22 -> 5036.4928 | N6: =Assumptions!N22 -> 5176.9617
B7: Goodwill | C7: 2961 | D7: 1736 | E7: 0 | F7: 0 | G7: 0 | H7: 0 | I7: 0 | J7: =Assumptions!J23 -> 0 | K7: =Assumptions!K23 -> 0 | L7: =Assumptions!L23 -> 0 | M7: =Assumptions!M23 -> 0 | N7: =Assumptions!N23 -> 0
A8: Capex | B8: Other Intangible assets | C8: 793 | D8: 196 | E8: 336 | F8: 224 | G8: 350 | H8: 548 | I8: 454 | J8: =Schedules_Populated!J72 -> 517.97957 | K8: =Schedules_Populated!K72 -> 610.12824 | L8: =Schedules_Populated!L72 -> 699.64408 | M8: =Schedules_Populated!M72 -> 817.77078 | N8: =Schedules_Populated!N72 -> 950.083
B9: Intangible assets under development | C9: 0 | D9: 17 | E9: 71 | F9: 298 | G9: 290 | H9: 89 | I9: 230 | J9: =Assumptions!J24 -> 184.6 | K9: =Assumptions!K24 -> 210.54 | L9: =Assumptions!L24 -> 200.496 | M9: =Assumptions!M24 -> 193.7204 | N9: =Assumptions!N24 -> 200.15096
A10: Capex | B10: Right of use assets | C10: 5484 | D10: 3965 | E10: 618 | F10: 586 | G10: 571 | H10: 591 | I10: 613 | J10: =Schedules_Populated!J73 -> 626.96075 | K10: =Schedules_Populated!K73 -> 637.3457 | L10: =Schedules_Populated!L73 -> 645.69404 | M10: =Schedules_Populated!M73 -> 655.31396 | N10: =Schedules_Populated!N73 -> 664.29856
B11: Financial Assets
B12: i. Investments | E12: 36269 | F12: 34529 | G12: 37935 | H12: 49184 | I12: 53384
B13: ii. Loans | C13: 585 | D13: 618 | E13: 0.2 | F13: 0.2 | G13: 0.2 | H13: 0.2 | I13: 0.1 | J13: =Assumptions!J27 -> 0.16 | K13: =Assumptions!K27 -> 0.154 | L13: =Assumptions!L27 -> 0.1596 | M13: =Assumptions!M27 -> 0.15604 | N13: =Assumptions!N27 -> 0.151696
B14: iii. Other Financial assets | C14: 185 | D14: 239 | E14: 36.5 | F14: 37 | G14: 37.5 | H14: 240 | I14: 298 | J14: =Assumptions!J28 -> 202.3 | K14: =Assumptions!K28 -> 201.77 | L14: =Assumptions!L28 -> 198.948 | M14: =Assumptions!M28 -> 214.1402 | N14: =Assumptions!N28 -> 215.54748
B15: Income tax assets (net) | C15: 584 | D15: 920 | E15: 0 | F15: 541 | G15: 545 | H15: 605 | I15: 584 | J15: =Assumptions!J29 -> 523.7 | K15: =Assumptions!K29 -> 553.78 | L15: =Assumptions!L29 -> 552.022 | M15: =Assumptions!M29 -> 558.2128 | N15: =Assumptions!N29 -> 555.03972
B16: Other Assets | C16: 40 | D16: 48 | E16: 1722 | F16: 1687 | G16: 2520 | H16: 2323 | I16: 2805 | J16: =Assumptions!J30 -> 2411.8 | K16: =Assumptions!K30 -> 2459.22 | L16: =Assumptions!L30 -> 2472.028 | M16: =Assumptions!M30 -> 2480.5572 | N16: =Assumptions!N30 -> 2501.4333
B17: Deferred tax assets (net) | C17: 0 | D17: 0 | E17: 0 | F17: 0 | G17: 141 | H17: 279 | I17: 47 | J17: =Assumptions!J31 -> 116.6 | K17: =Assumptions!K31 -> 102.74 | L17: =Assumptions!L31 -> 122.776 | M17: =Assumptions!M31 -> 124.1924 | N17: =Assumptions!N31 -> 113.14376
B18: Total Non-current assets | C18: =SUM(C5:C17) -> 10910 | D18: =SUM(D5:D17) -> 7953 | E18: =SUM(E5:E17) -> 55186.7 | F18: =SUM(F5:F17) -> 53279.2 | G18: =SUM(G5:G17) -> 57861.7 | H18: =SUM(H5:H17) -> 84716.2 | I18: =SUM(I5:I17) -> 92717.1 | J18: =SUM(J5:J17) -> 37471.465 | ... N18: =SUM(N5:N17) -> 49400.001
B19: Current assets
B20: Inventories | E20: 3214 | F20: 3049 | G20: 3532 | H20: 5443 | I20: 5318
B21: Financial assets
B22: i. Investments | C22: 13862 | D22: 9815 | E22: 1219 | F22: 8416 | G22: 4100 | H22: 0 | I22: 3912 | J22: =Schedules_Populated!J5 -> 4019.6356 | K22: =Schedules_Populated!K5 -> 3878.0218 | L22: =Schedules_Populated!L5 -> 3552.1879 | M22: =Schedules_Populated!M5 -> 3813.3642 | N22: =Schedules_Populated!N5 -> 3842.7031
B23: ii. Trade receivables | C23: 9437 | D23: 12927 | E23: 1978 | F23: 1280 | G23: 2034 | H23: 3285 | I23: 4597 | J23: =Schedules_Populated!J6 -> 4076.2619 | K23: =Schedules_Populated!K6 -> 4037.7646 | L23: =Schedules_Populated!L6 -> 4038.4393 | M23: =Schedules_Populated!M6 -> 4149.872 | N23: =Schedules_Populated!N6 -> 4271.9013
B24: iii. Cash and cash equivalents | C24: 1652 | D24: 2627 | E24: 21 | F24: 41 | G24: 35 | H24: 1785 | I24: 2660 | J24: =CFS!B20 -> 24815.649 | K24: =CFS!C20 -> 50730.112 | L24: =CFS!D20 -> 87073.599 | M24: =CFS!E20 -> 133840.83 | N24: =CFS!F20 -> 193982.31
B25: iv. Loans | C25: 273 | D25: 77 | E25: 17 | F25: 23 | G25: 30.5 | H25: 30 | I25: 33 | J25: =Schedules_Populated!J7 -> 37.639332 | K25: =Schedules_Populated!K7 -> 38.574388 | L25: =Schedules_Populated!L7 -> 38.722962 | M25: =Schedules_Populated!M7 -> 38.272128 | N25: =Schedules_Populated!N7 -> 39.00615
B26: v. Other financial assets | C26: 1141 | D26: 7091 | E26: 660 | F26: 1324 | G26: 2593 | H26: 2602 | I26: 3419 | J26: =Schedules_Populated!J8 -> 3412.7871 | K26: =Schedules_Populated!K8 -> 3496.1631 | L26: =Schedules_Populated!L8 -> 3435.0408 | M26: =Schedules_Populated!M8 -> 3493.6732 | N26: =Schedules_Populated!N8 -> 3563.6517
B27: vi. Other Bank Balances | E27: 8 | F27: 3006 | G27: 3007 | H27: 963 | I27: 168 | J27: 57687 | K27: 57687 | L27: 57687 | M27: 57687 | N27: 57687
B28: Other assets | C28: 1424 | D28: 862 | E28: 1325 | F28: 958 | G28: 1461 | H28: 1560 | I28: 2508 | J28: =Schedules_Populated!J9 -> 2297.1213 | K28: =Schedules_Populated!K9 -> 2314.9107 | L28: =Schedules_Populated!L9 -> 2299.1559 | M28: =Schedules_Populated!M9 -> 2315.4248 | N28: =Schedules_Populated!N9 -> 2400.4881
B29: Assets classified as held for Sale | H29: 0 | I29: 20
B30: Total current assets | C30: =SUM(C22:C28) -> 27789 | D30: =SUM(D22:D28) -> 33399 | E30: =SUM(E20:E28) -> 8442 | F30: =SUM(F20:F28) -> 18097 | G30: =SUM(G20:G28) -> 16792.5 | H30: =SUM(H20:H29) -> 15668 | I30: =SUM(I20:I29) -> 22635 | J30: =SUM(J22:J28) -> 96346.094 | K30: =SUM(K22:K28) -> 122182.55 | L30: =SUM(L22:L28) -> 158124.15 | M30: =SUM(M22:M28) -> 205338.43 | N30: =SUM(N22:N28) -> 265787.06
B31: Total assets | C31: =C18+C30 -> 38699 | D31: =D18+D30 -> 41352 | E31: =E18+E30 -> 63628.7 | F31: =F18+F30 -> 71376.2 | G31: =G18+G30 -> 74654.2 | H31: =H18+H30 -> 100384.2 | I31: =I18+I30 -> 115352.1 | J31: =J18+J30 -> 133817.56 | ... N31: =N18+N30 -> 315187.06
B32: Equity and liabilities
B33: Equity
B34: Equity share capital | C34: 375 | D34: 597 | E34: 151 | F34: 151 | G34: 151 | H34: 157 | I34: 157 | J34: =Assumptions!L34 -> 157 | K34: =Assumptions!K34 -> 157 | L34: =Assumptions!L34 -> 157 | M34: =Assumptions!M34 -> 157 | N34: =Assumptions!N34 -> 157
B35: Non controlling Interest | C35: 2229 | D35: 2230 | E35: 19 | F35: 0 | G35: 0 | H35: 0 | I35: 0 | J35: =Assumptions!J35 -> 0 | K35: =Assumptions!K35 -> 0 | L35: =Assumptions!L35 -> 0 | M35: =Assumptions!M35 -> 0 | N35: =Assumptions!N35 -> 0
B36: Other equity | C36: -13492 | D36: -9432 | E36: 49262 | F36: 52350 | G36: 55182 | H36: 74443 | I36: 85479 | J36: =Assumptions!J36 -> 105098.36 | K36: =Assumptions!K36 -> 133419.27 | L36: =Assumptions!L36 -> 171973.64 | M36: =Assumptions!M36 -> 222138.3 | N36: =Assumptions!N36 -> 285395.03
B37: Total Equity | C37: =SUM(C34:C36) -> -10888 | D37: =SUM(D34:D36) -> -6605 | E37: =SUM(E34:E36) -> 49432 | F37: =SUM(F34:F36) -> 52501 | G37: =SUM(G34:G36) -> 55333 | H37: =SUM(H34:H36) -> 74600 | I37: =SUM(I34:I36) -> 85636 | J37: =SUM(J34:J36) -> 105255.36 | ... N37: =SUM(N34:N36) -> 285552.03
B38: Liabilities
B39: Non-current Liabilities
B40: Financial Liabilities
B41: i. Borrowings | C41: 1483 | D41: 850 | E41: 5 | F41: 2.8 | G41: 0 | H41: 0 | I41: 0 | J41: =Schedules_Populated!J42 -> 0.12099114 | K41: =Schedules_Populated!K42 -> 0.049258597 | L41: =Schedules_Populated!L42 -> 0.0038212058 | M41: =Schedules_Populated!M42 -> 0.005140706 | N41: =Schedules_Populated!N42 -> 0.041393374
B42: ii. Lease Liabilities | C42: 4314 | D42: 2964 | E42: 60 | F42: 39 | G42: 33 | H42: 25 | I42: 67 | J42: =Schedules_Populated!J46 -> 72.857143 | K42: =Schedules_Populated!K46 -> 75.5882 | L42: =Schedules_Populated!L46 -> 78.913397 | M42: =Schedules_Populated!M46 -> 82.828257 | N42: =Schedules_Populated!N46 -> 87.12069
B43: Other non-current Liabilities | E43: 2116 | F43: 2129 | G43: 2181 | H43: 2585 | I43: 3162 | J43: =Assumptions!J38 -> 2682.9 | K43: =Assumptions!K38 -> 2711.26 | L43: =Assumptions!L38 -> 2682.174 | M43: =Assumptions!M38 -> 2729.2376 | N43: =Assumptions!N38 -> 2751.9632
B44: Provisions | C44: 812 | D44: 940 | E44: 52 | F44: 45 | G44: 84 | H44: 87 | I44: 145 | J44: =Assumptions!J39 -> 102.2 | K44: =Assumptions!K39 -> 105.98 | L44: =Assumptions!L39 -> 104.652 | M44: =Assumptions!M39 -> 107.0748 | N44: =Assumptions!N39 -> 109.54352
B45: Deferred tax liabilities (net) | C45: 123 | D45: 0 | E45: 658 | F45: 445 | G45: 0 | H45: 321 | I45: 389 | J45: =Assumptions!J40 -> 362.2 | K45: =Assumptions!K40 -> 338.18 | L45: =Assumptions!L40 -> 314.932 | M45: =Assumptions!M40 -> 334.6468 | N45: =Assumptions!N40 -> 337.27632
B46: Total non-current liabilities | C46: =SUM(C41:C45) -> 6732 | D46: =SUM(D41:D45) -> 4754 | E46: =SUM(E41:E45) -> 2891 | F46: =SUM(F41:F45) -> 2660.8 | G46: =SUM(G41:G45) -> 2298 | H46: =SUM(H41:H45) -> 3018 | I46: =SUM(I41:I45) -> 3763 | J46: =SUM(J41:J45) -> 3220.2781 | ... N46: =SUM(N41:N45) -> 3285.9452
B47: Current Liabilities
B48: Outstanding Dues of creditors & Enterprises | C48: 547 | D48: 1067 | E48: 7500 | F48: 10168 | G48: 9765 | H48: 13675 | I48: 16988 | J48: =Schedules_Populated!J12 -> 17160.543 | K48: =Schedules_Populated!K12 -> 17436.854 | L48: =Schedules_Populated!L12 -> 17113.234 | M48: =Schedules_Populated!M12 -> 17385.059 | N48: =Schedules_Populated!N12 -> 17779.4
B49: Financial Liabilities
B50: i. Borrowings | C50: 6855 | D50: 6012 | E50: 106 | F50: 489 | G50: 382 | H50: 1216 | I50: 33 | J50: =Schedules_Populated!J14 -> 34.529009 | K50: =Schedules_Populated!K14 -> 36.333241 | L50: =Schedules_Populated!L14 -> 38.197804 | M50: =Schedules_Populated!M14 -> 40.106566 | N50: =Schedules_Populated!N14 -> 42.075898
B51: ii. Lease Liabilities | C51: 1456 | D51: 1582 | E51: 10 | F51: 7.4 | G51: 8 | H51: 7 | I51: 18 | J51: =Schedules_Populated!J15 -> 16.392857 | K51: =Schedules_Populated!K15 -> 18.1243 | L51: =Schedules_Populated!L15 -> 19.484728 | M51: =Schedules_Populated!M15 -> 20.489774 | N51: =Schedules_Populated!N15 -> 21.363242
B52: iii. Trade payables | C52: 2498 | D52: 2878 | E52: 0 | F52: 0 | G52: 0 | H52: 0 | I52: 0 | J52: =Schedules_Populated!J16 -> 0 | K52: =Schedules_Populated!K16 -> 0 | L52: =Schedules_Populated!L16 -> 0 | M52: =Schedules_Populated!M16 -> 0 | N52: =Schedules_Populated!N16 -> 0
B53: iv. Other Financial liabilities | C53: 30008 | D53: 29930 | E53: 904 | F53: 1272 | G53: 2027 | H53: 2290 | I53: 2224 | J53: =Schedules_Populated!J17 -> 2526.8571 | K53: =Schedules_Populated!K17 -> 2566.6115 | L53: =Schedules_Populated!L17 -> 2621.7014 | M53: =Schedules_Populated!M17 -> 2606.3595 | N53: =Schedules_Populated!N17 -> 2639.1374
B54: Provisions | C54: 820 | D54: 998 | E54: 681 | F54: 743 | G54: 861 | H54: 1083 | I54: 1312 | J54: =Schedules_Populated!J18 -> 1363.6489 | K54: =Schedules_Populated!K18 -> 1374.0811 | L54: =Schedules_Populated!L18 -> 1364.9136 | M54: =Schedules_Populated!M18 -> 1375.6534 | N54: =Schedules_Populated!N18 -> 1406.799
B55: Other current liabilities | C55: 671 | D55: 736 | E55: 1409 | F55: 2680 | G55: 2869 | H55: 3337 | I55: 4175 | J55: =Schedules_Populated!J19 -> 4239.8479 | K55: =Schedules_Populated!K19 -> 4405.7618 | L55: =Schedules_Populated!L19 -> 4334.7185 | M55: =Schedules_Populated!M19 -> 4360.5591 | N55: =Schedules_Populated!N19 -> 4460.2083
B56: Current tax liabilities (net) | E56: 696 | F56: 855 | G56: 1111 | H56: 1158 | I56: 1203
B57: Total Current Liabilities | C57: =SUM(C48:C55) -> 42855 | D57: =SUM(D48:D55) -> 43203 | E57: =SUM(E48:E56) -> 11306 | F57: =SUM(F48:F56) -> 16214.4 | G57: =SUM(G48:G56) -> 17023 | H57: =SUM(H48:H56) -> 22766 | I57: =SUM(I48:I56) -> 25953 | J57: =SUM(J48:J55) -> 25341.819 | K57: =SUM(K48:K55) -> 25837.766 | L57: =SUM(L48:L55) -> 25492.25 | M57: =SUM(M48:M55) -> 25788.227 | N57: =SUM(N48:N55) -> 26348.984
B58: Total liabilities | C58: =C46+C57 -> 49587 | D58: =D46+D57 -> 47957 | E58: =E46+E57 -> 14197 | F58: =F46+F57 -> 18875.2 | G58: =G46+G57 -> 19321 | H58: =H46+H57 -> 25784 | I58: =I46+I57 -> 29716 | J58: =J46+J57 -> 28562.097 | ... N58: =N46+N57 -> 29634.929
B59: Total Equity and liabilities | C59: =C37+C58 -> 38699 | D59: =D37+D58 -> 41352 | E59: =E37+E58 -> 63629 | F59: =F37+F58 -> 71376.2 | G59: =G37+G58 -> 74654 | H59: =H37+H58 -> 100384 | I59: =I37+I58 -> 115352 | J59: =J37+J58 -> 133817.46 | ... N59: =N37+N58 -> 315186.96
B61: Balancing Check | C61: =C31-C59 -> 0 | D61: =D31-D59 -> 0 | E61: =E31-E59 -> -0.3 | F61: =F31-F59 -> 0 | G61: =G31-G59 -> 0.2 | H61: =H31-H59 -> 0.2 | I61: =I31-I59 -> 0.1 | J61: =J31-J59 -> 0.1 | ... N61: =N31-N59 -> 0.1

Sheet CFS
A1: Cash Flow Statement ( All Amount in ₹ Crores, Unless otherwise stated) | B1: 2025E | C1: 2026E | D1: 2027E | E1: 2028E | F1: 2029E
A2: Net Profit | B2: ='Profit & Loss Statement'!J25 -> 19619.362 | C2: ='Profit & Loss Statement'!K25 -> 28320.909 | D2: ='Profit & Loss Statement'!L25 -> 38554.371 | E2: ='Profit & Loss Statement'!M25 -> 50164.654 | F2: ='Profit & Loss Statement'!N25 -> 63256.735 | H2: I/S
A3: Add Finance Costs | B3: ='Profit & Loss Statement'!J12 -> 208.42213 | C3: ='Profit & Loss Statement'!K12 -> 208.0012 | D3: ='Profit & Loss Statement'!L12 -> 232.38795 | E3: ='Profit & Loss Statement'!M12 -> 242.84088 | F3: ='Profit & Loss Statement'!N12 -> 240.07668 | H3: I/S
A4: Add Depreciation | B4: ='Profit & Loss Statement'!J11 -> 6453.3954 | C4: ='Profit & Loss Statement'!K11 -> 6977.0334 | D4: ='Profit & Loss Statement'!L11 -> 8146.8453 | E4: ='Profit & Loss Statement'!M11 -> 9146.126 | F4: ='Profit & Loss Statement'!N11 -> 10473.128 | H4: I/S | I4: Derived Statement
A5: Less Change in Net Working Capital | B5: =-Schedules_Populated!J22 -> 1217.3735 | C5: =-Schedules_Populated!K22 -> 573.95802 | D5: =-Schedules_Populated!L22 -> 56.371516 | E5: =-Schedules_Populated!M22 -> -151.08202 | F5: =-Schedules_Populated!N22 -> 253.61227 | H5: WC Schedule/BS
A6: Cash Flow from Operating Activities | B6: =SUM(B2:B5) -> 27498.553 | C6: =SUM(C2:C5) -> 36079.902 | D6: =SUM(D2:D5) -> 46989.975 | E6: =SUM(E2:E5) -> 59402.539 | F6: =SUM(F2:F5) -> 74223.552
A8: Other Changes in Investments/Liabilitie/Others | B8: =SUM('Balance Sheet'!I6:I7,'Balance Sheet'!I9,'Balance Sheet'!I13:I17,'Balance Sheet'!J43:J45)-SUM('Balance Sheet'!J6:J7,'Balance Sheet'!J9,'Balance Sheet'!J13:J17,'Balance Sheet'!I43:I45) -> 2743.54 | C8: =SUM('Balance Sheet'!J6:J7,'Balance Sheet'!J9,'Balance Sheet'!J13:J17,'Balance Sheet'!K43:K45)-SUM('Balance Sheet'!K6:K7,'Balance Sheet'!K9,'Balance Sheet'!K13:K17,'Balance Sheet'!J43:J45) -> -280.004 | D8: =SUM('Balance Sheet'!K6:K7,'Balance Sheet'!K9,'Balance Sheet'!K13:K17,'Balance Sheet'!L43:L45)-SUM('Balance Sheet'!L6:L7,'Balance Sheet'!L9,'Balance Sheet'!L13:L17,'Balance Sheet'!K43:K45) -> 48.1704 | E8: =SUM('Balance Sheet'!L6:L7,'Balance Sheet'!L9,'Balance Sheet'!L13:L17,'Balance Sheet'!M43:M45)-SUM('Balance Sheet'!M6:M7,'Balance Sheet'!M9,'Balance Sheet'!M13:M17,'Balance Sheet'!L43:L45) -> -176.11904 | F8: =SUM('Balance Sheet'!M6:M7,'Balance Sheet'!M9,'Balance Sheet'!M13:M17,'Balance Sheet'!N43:N45)-SUM('Balance Sheet'!N6:N7,'Balance Sheet'!N9,'Balance Sheet'!N13:N17,'Balance Sheet'!M43:M45) -> -127.1329
A9: Capital Expenditure | B9: =-Schedules_Populated!J106 -> -7884 | C9: =-Schedules_Populated!K106 -> -9680.0931 | D9: =-Schedules_Populated!L106 -> -10465.55 | E9: =-Schedules_Populated!M106 -> -12220.268 | F9: =-Schedules_Populated!N106 -> -13719.189 | H9: Capex Schedule/BS
A10: Cash Flow from Investing Activities | B10: =B9+B8 -> -5140.46 | C10: =C9+C8 -> -9960.0971 | D10: =D9+D8 -> -10417.38 | E10: =E9+E8 -> -12396.387 | F10: =F9+F8 -> -13846.322
A12: Changes to Equity | B12: ='Balance Sheet'!J34-'Balance Sheet'!I34 -> 0 | C12: ='Balance Sheet'!K34-'Balance Sheet'!J34 -> 0 | D12: ='Balance Sheet'!L34-'Balance Sheet'!K34 -> 0 | E12: ='Balance Sheet'!M34-'Balance Sheet'!L34 -> 0 | F12: ='Balance Sheet'!N34-'Balance Sheet'!M34 -> 0 | H12: B/S
A13: Net Loans Raised for the long term | B13: =Schedules_Populated!J61+Schedules_Populated!J66 -> 5.978134 | C13: =Schedules_Populated!K61+Schedules_Populated!K66 -> 2.6593248 | D13: =Schedules_Populated!L61+Schedules_Populated!L66 -> 3.2797592 | E13: =Schedules_Populated!M61+Schedules_Populated!M66 -> 3.9161798 | F13: =Schedules_Populated!N61+Schedules_Populated!N66 -> 4.328686
A14: Finance Costs Paid | B14: =-B3 -> -208.42213 | C14: =-C3 -> -208.0012 | D14: =-D3 -> -232.38795 | E14: =-E3 -> -242.84088 | F14: =-F3 -> -240.07668 | H14: I/S
A15: Dividend Paid | B15: 0 | C15: 0 | D15: 0 | E15: 0 | F15: 0 | H15: I/S
A16: Cash Flow from Financing Activities | B16: =SUM(B12:B15) -> -202.444 | C16: =SUM(C12:C15) -> -205.34187 | D16: =SUM(D12:D15) -> -229.10819 | E16: =SUM(E12:E15) -> -238.9247 | F16: =SUM(F12:F15) -> -235.748
A18: Total Cash Flow | B18: =B6+B10+B16 -> 22155.649 | C18: =C6+C10+C16 -> 25914.463 | D18: =D6+D10+D16 -> 36343.487 | E18: =E6+E10+E16 -> 46767.228 | F18: =F6+F10+F16 -> 60141.482
A19: Beginning Cash Balance | B19: ='Balance Sheet'!I24 -> 2660 | C19: ='Balance Sheet'!J24 -> 24815.649 | D19: ='Balance Sheet'!K24 -> 50730.112 | E19: ='Balance Sheet'!L24 -> 87073.599 | F19: ='Balance Sheet'!M24 -> 133840.83 | H19: B/S
A20: Closing Cash Balance in Balance Sheet | B20: =B18+B19 -> 24815.649 | C20: =C18+C19 -> 50730.112 | D20: =D18+D19 -> 87073.599 | E20: =E18+E19 -> 133840.83 | F20: =F18+F19 -> 193982.31

Sheet Schedules_Populated
B2: Working Capital Schedule | C2: FY18 | D2: FY19 | E2: FY20 | F2: FY21 | G2: FY22 | H2: FY23 | I2: FY24 | J2: FY25E | K2: FY26E | L2: FY27E | M2: FY28E | N2: FY29E
B3: Current assets (except cash & equivalents)
B4: Financial assets
B5: i. Investments | C5: ='Balance Sheet'!C22 -> 13862 | D5: ='Balance Sheet'!D22 -> 9815 | E5: ='Balance Sheet'!E22 -> 1219 | F5: ='Balance Sheet'!F22 -> 8416 | G5: ='Balance Sheet'!G22 -> 4100 | H5: ='Balance Sheet'!H22 -> 0 | I5: ='Balance Sheet'!I22 -> 3912 | J5: =J25*'Profit & Loss Statement'!J$5/365 -> 4019.6356 | K5: =K25*'Profit & Loss Statement'!K$5/365 -> 3878.0218 | L5: =L25*'Profit & Loss Statement'!L$5/365 -> 3552.1879 | M5: =M25*'Profit & Loss Statement'!M$5/365 -> 3813.3642 | N5: =N25*'Profit & Loss Statement'!N$5/365 -> 3842.7031 | P5: How to forecast forecast WC Schedule
B6: ii. Trade receivables | C6: ='Balance Sheet'!C23 -> 9437 | D6: ='Balance Sheet'!D23 -> 12927 | E6: ='Balance Sheet'!E23 -> 1978 | F6: ='Balance Sheet'!F23 -> 1280 | G6: ='Balance Sheet'!G23 -> 2034 | H6: ='Balance Sheet'!H23 -> 3285 | I6: ='Balance Sheet'!I23 -> 4597 | J6: =J26*'Profit & Loss Statement'!J$5/365 -> 4076.2619 | K6: =K26*'Profit & Loss Statement'!K$5/365 -> 4037.7646 | L6: =L26*'Profit & Loss Statement'!L$5/365 -> 4038.4393 | M6: =M26*'Profit & Loss Statement'!M$5/365 -> 4149.872 | N6: =N26*'Profit & Loss Statement'!N$5/365 -> 4271.9013 | P6: 1. Convert CA/CL into DSO | S6: DSO = (CA/CL)x365/Sales
B7: iii. Loans | C7: ='Balance Sheet'!C25 -> 273 | D7: ='Balance Sheet'!D25 -> 77 | E7: ='Balance Sheet'!E25 -> 17 | F7: ='Balance Sheet'!F25 -> 23 | G7: ='Balance Sheet'!G25 -> 30.5 | H7: ='Balance Sheet'!H25 -> 30 | I7: ='Balance Sheet'!I25 -> 33 | J7: =J27*'Profit & Loss Statement'!J$5/365 -> 37.639332 | K7: =K27*'Profit & Loss Statement'!K$5/365 -> 38.574388 | L7: =L27*'Profit & Loss Statement'!L$5/365 -> 38.722962 | M7: =M27*'Profit & Loss Statement'!M$5/365 -> 38.272128 | N7: =N27*'Profit & Loss Statement'!N$5/365 -> 39.00615 | P7: 2. Forecast the DSO
B8: iv. Other financial assets | C8: ='Balance Sheet'!C26 -> 1141 | D8: ='Balance Sheet'!D26 -> 7091 | E8: ='Balance Sheet'!E26 -> 660 | F8: ='Balance Sheet'!F26 -> 1324 | G8: ='Balance Sheet'!G26 -> 2593 | H8: ='Balance Sheet'!H26 -> 2602 | I8: ='Balance Sheet'!I26 -> 3419 | J8: =J28*'Profit & Loss Statement'!J$5/365 -> 3412.7871 | K8: =K28*'Profit & Loss Statement'!K$5/365 -> 3496.1631 | L8: =L28*'Profit & Loss Statement'!L$5/365 -> 3435.0408 | M8: =M28*'Profit & Loss Statement'!M$5/365 -> 3493.6732 | N8: =N28*'Profit & Loss Statement'!N$5/365 -> 3563.6517 | P8: 3. Calculate Forecasted CA/CL from Forecasted DSO | S8: (CA/CL) = DSOxSales/365
B9: Other assets | C9: ='Balance Sheet'!C28 -> 1424 | D9: ='Balance Sheet'!D28 -> 862 | E9: ='Balance Sheet'!E28 -> 1325 | F9: ='Balance Sheet'!F28 -> 958 | G9: ='Balance Sheet'!G28 -> 1461 | H9: ='Balance Sheet'!H28 -> 1560 | I9: ='Balance Sheet'!I28 -> 2508 | J9: =J29*'Profit & Loss Statement'!J$5/365 -> 2297.1213 | K9: =K29*'Profit & Loss Statement'!K$5/365 -> 2314.9107 | L9: =L29*'Profit & Loss Statement'!L$5/365 -> 2299.1559 | M9: =M29*'Profit & Loss Statement'!M$5/365 -> 2315.4248 | N9: =N29*'Profit & Loss Statement'!N$5/365 -> 2400.4881
B10: Total Current Assets (except cash & equivalents) | C10: =SUM(C5:C9) -> 26137 | D10: =SUM(D5:D9) -> 30772 | E10: =SUM(E5:E9) -> 5199 | F10: =SUM(F5:F9) -> 12001 | G10: =SUM(G5:G9) -> 10218.5 | H10: =SUM(H5:H9) -> 7477 | I10: =SUM(I5:I9) -> 14469 | J10: =SUM(J5:J9) -> 13843.445 | ... N10: =SUM(N5:N9) -> 14117.75
B11: Current Liabilities
B12: Outstanding Dues of creditors & Enterprises | C12: ='Balance Sheet'!C48 -> 547 | D12: ='Balance Sheet'!D48 -> 1067 | E12: ='Balance Sheet'!E48 -> 7500 | F12: ='Balance Sheet'!F48 -> 10168 | G12: ='Balance Sheet'!G48 -> 9765 | H12: ='Balance Sheet'!H48 -> 13675 | I12: ='Balance Sheet'!I48 -> 16988 | J12: =J31*'Profit & Loss Statement'!J$5/365 -> 17160.543 | K12: =K31*'Profit & Loss Statement'!K$5/365 -> 17436.854 | L12: =L31*'Profit & Loss Statement'!L$5/365 -> 17113.234 | M12: =M31*'Profit & Loss Statement'!M$5/365 -> 17385.059 | N12: =N31*'Profit & Loss Statement'!N$5/365 -> 17779.4 | P12: DSO = (CA or CL)x365/Sales
B13: Financial Liabilities | P13: (CA/CL) = DSOxSales/365
B14: i. Borrowings | C14: ='Balance Sheet'!C50 -> 6855 | D14: ='Balance Sheet'!D50 -> 6012 | E14: ='Balance Sheet'!E50 -> 106 | F14: ='Balance Sheet'!F50 -> 489 | G14: ='Balance Sheet'!G50 -> 382 | H14: ='Balance Sheet'!H50 -> 1216 | I14: ='Balance Sheet'!I50 -> 33 | J14: =J43 -> 34.529009 | K14: =K43 -> 36.333241 | L14: =L43 -> 38.197804 | M14: =M43 -> 40.106566 | N14: =N43 -> 42.075898
B15: ii. Lease Liabilities | C15: ='Balance Sheet'!C51 -> 1456 | D15: ='Balance Sheet'!D51 -> 1582 | E15: ='Balance Sheet'!E51 -> 10 | F15: ='Balance Sheet'!F51 -> 7.4 | G15: ='Balance Sheet'!G51 -> 8 | H15: ='Balance Sheet'!H51 -> 7 | I15: ='Balance Sheet'!I51 -> 18 | J15: =J47 -> 16.392857 | K15: =K47 -> 18.1243 | L15: =L47 -> 19.484728 | M15: =M47 -> 20.489774 | N15: =N47 -> 21.363242
B16: iii. Trade payables | C16: ='Balance Sheet'!C52 -> 2498 | D16: ='Balance Sheet'!D52 -> 2878 | E16: ='Balance Sheet'!E52 -> 0 | F16: ='Balance Sheet'!F52 -> 0 | G16: ='Balance Sheet'!G52 -> 0 | H16: ='Balance Sheet'!H52 -> 0 | I16: ='Balance Sheet'!I52 -> 0 | J16: =J35*'Profit & Loss Statement'!J$5/365 -> 0 | K16: =K35*'Profit & Loss Statement'!K$5/365 -> 0 | L16: =L35*'Profit & Loss Statement'!L$5/365 -> 0 | M16: =M35*'Profit & Loss Statement'!M$5/365 -> 0 | N16: =N35*'Profit & Loss Statement'!N$5/365 -> 0 | P16: Whenever we are forecasting on the basis of Average
B17: iv. Other Financial liabilities | C17: ='Balance Sheet'!C53 -> 30008 | D17: ='Balance Sheet'!D53 -> 29930 | E17: ='Balance Sheet'!E53 -> 904 | F17: ='Balance Sheet'!F53 -> 1272 | G17: ='Balance Sheet'!G53 -> 2027 | H17: ='Balance Sheet'!H53 -> 2290 | I17: ='Balance Sheet'!I53 -> 2224 | J17: =J36*'Profit & Loss Statement'!J$5/365 -> 2526.8571 | K17: =K36*'Profit & Loss Statement'!K$5/365 -> 2566.6115 | L17: =L36*'Profit & Loss Statement'!L$5/365 -> 2621.7014 | M17: =M36*'Profit & Loss Statement'!M$5/365 -> 2606.3595 | N17: =N36*'Profit & Loss Statement'!N$5/365 -> 2639.1374
B18: Provisions | C18: ='Balance Sheet'!C54 -> 820 | D18: ='Balance Sheet'!D54 -> 998 | E18: ='Balance Sheet'!E54 -> 681 | F18: ='Balance Sheet'!F54 -> 743 | G18: ='Balance Sheet'!G54 -> 861 | H18: ='Balance Sheet'!H54 -> 1083 | I18: ='Balance Sheet'!I54 -> 1312 | J18: =J37*'Profit & Loss Statement'!J$5/365 -> 1363.6489 | K18: =K37*'Profit & Loss Statement'!K$5/365 -> 1374.0811 | L18: =L37*'Profit & Loss Statement'!L$5/365 -> 1364.9136 | M18: =M37*'Profit & Loss Statement'!M$5/365 -> 1375.6534 | N18: =N37*'Profit & Loss Statement'!N$5/365 -> 1406.799 | P18: If it is Balance Sheet
B19: Other current liabilities | C19: ='Balance Sheet'!C55 -> 671 | D19: ='Balance Sheet'!D55 -> 736 | E19: ='Balance Sheet'!E55 -> 1409 | F19: ='Balance Sheet'!F55 -> 2680 | G19: ='Balance Sheet'!G55 -> 2869 | H19: ='Balance Sheet'!H55 -> 3337 | I19: ='Balance Sheet'!I55 -> 4175 | J19: =J38*'Profit & Loss Statement'!J$5/365 -> 4239.8479 | K19: =K38*'Profit & Loss Statement'!K$5/365 -> 4405.7618 | L19: =L38*'Profit & Loss Statement'!L$5/365 -> 4334.7185 | M19: =M38*'Profit & Loss Statement'!M$5/365 -> 4360.5591 | N19: =N38*'Profit & Loss Statement'!N$5/365 -> 4460.2083 | P19: Use Weighted Average
B20: Total Current Liabilities | C20: =SUM(C12:C19) -> 42855 | D20: =SUM(D12:D19) -> 43203 | E20: =SUM(E12:E19) -> 10610 | F20: =SUM(F12:F19) -> 15359.4 | G20: =SUM(G12:G19) -> 15912 | H20: =SUM(H12:H19) -> 21608 | I20: =SUM(I12:I19) -> 24750 | J20: =SUM(J12:J19) -> 25341.819 | ... N20: =SUM(N12:N19) -> 26348.984 | P20: Because I want to give more weightage to receny years, as balance sheet is not that volatile
B21: Net Working Capital (excluding cash) | C21: =C10-C20 -> -16718 | D21: =D10-D20 -> -12431 | E21: =E10-E20 -> -5411 | F21: =F10-F20 -> -3358.4 | G21: =G10-G20 -> -5693.5 | H21: =H10-H20 -> -14131 | I21: =I10-I20 -> -10281 | J21: =J10-J20 -> -11498.374 | ... N21: =N10-N20 -> -12231.233 | P21: If it's p&L Statement use Simple average
B22: Changes in Net Working Capital | D22: =D21-C21 -> 4287 | E22: =E21-D21 -> 7020 | F22: =F21-E21 -> 2052.6 | G22: =G21-F21 -> -2335.1 | H22: =H21-G21 -> -8437.5 | I22: =I21-H21 -> 3850 | J22: =J21-I21 -> -1217.3735 | K22: =K21-J21 -> -573.95802 | ... N22: =N21-M21 -> -253.61227
A23: DSO | B23: Current Asset as days of sales | C23: =C2 -> FY18 | D23: =D2 -> FY19 | E23: =E2 -> FY20 | F23: =F2 -> FY21 | G23: =G2 -> FY22 | H23: =H2 -> FY23 | I23: =I2 -> FY24 | J23: =J2 -> FY25E | ... N23: =N2 -> FY29E
B24: Financial assets
B25: i. Investments | C25: =C5*365/'Profit & Loss Statement'!C$5 -> 108.20192 | D25: =D5*365/'Profit & Loss Statement'!D$5 -> 60.682888 | E25: =E5*365/'Profit & Loss Statement'!E$5 -> 5.8807164 | F25: =F5*365/'Profit & Loss Statement'!F$5 -> 43.651452 | G25: =G5*365/'Profit & Loss Statement'!G$5 -> 16.942149 | H25: =H5*365/'Profit & Loss Statement'!H$5 -> 0 | I25: =I5*365/'Revenue Model'!I$3 -> 10.065559 | J25: =I25*40%+H25*40%+G25*10%+F25*10% -> 10.085584 | K25: =J25*40%+I25*40%+H25*10%+G25*10% -> 9.7546717 | L25: =K25*40%+J25*40%+I25*10%+H25*10% -> 8.9426579 | M25: =L25*40%+K25*40%+J25*10%+I25*10% -> 9.494046 | N25: =M25*40%+L25*40%+K25*10%+J25*10% -> 9.3587071
B26: ii. Trade receivables | C26: =C6*365/'Profit & Loss Statement'!C$5 -> 73.661919 | D26: =D6*365/'Profit & Loss Statement'!D$5 -> 79.923352 | E26: =E6*365/'Profit & Loss Statement'!E$5 -> 9.5422945 | F26: =F6*365/'Profit & Loss Statement'!F$5 -> 6.6390041 | G26: =G6*365/'Profit & Loss Statement'!G$5 -> 8.4049587 | H26: =H6*365/'Profit & Loss Statement'!H$5 -> 10.126045 | I26: =I6*365/'Revenue Model'!I$3 -> 11.82806 | J26: =I26*40%+H26*30%+G26*10%+F26*10%+E26*10% -> 10.227663 | K26: =J26*40%+I26*30%+H26*10%+G26*10%+F26*10% -> 10.156484 | L26: =K26*40%+J26*30%+I26*10%+H26*10%+G26*10% -> 10.166799 | M26: =L26*40%+K26*30%+J26*10%+I26*10%+H26*10% -> 10.331842 | N26: =M26*40%+L26*30%+K26*10%+J26*10%+I26*10% -> 10.403997
B27: iii. Loans | C27: =C7*365/'Profit & Loss Statement'!C$5 -> 2.1309425 | D27: =D7*365/'Profit & Loss Statement'!D$5 -> 0.47606545 | E27: =E7*365/'Profit & Loss Statement'!E$5 -> 0.082011631 | F27: =F7*365/'Profit & Loss Statement'!F$5 -> 0.11929461 | G27: =G7*365/'Profit & Loss Statement'!G$5 -> 0.12603306 | H27: =H7*365/'Profit & Loss Statement'!H$5 -> 0.092475298 | I27: =I7*365/'Revenue Model'!I$3 -> 0.084908853 | J27: =I27*40%+H27*30%+G27*10%+F27*10%+E27*10% -> 0.09444006 | K27: =J27*40%+I27*30%+H27*10%+G27*10%+F27*10% -> 0.097028976 | L27: =K27*40%+J27*30%+I27*10%+H27*10%+G27*10% -> 0.097485329 | M27: =L27*40%+K27*30%+J27*10%+I27*10%+H27*10% -> 0.095285245 | N27: =M27*40%+L27*30%+K27*10%+J27*10%+I27*10% -> 0.094997486
B28: iv. Other financial assets | C28: =C8*365/'Profit & Loss Statement'!C$5 -> 8.9062467 | D28: =D8*365/'Profit & Loss Statement'!D$5 -> 43.8413 | E28: =E8*365/'Profit & Loss Statement'!E$5 -> 3.183981 | F28: =F8*365/'Profit & Loss Statement'!F$5 -> 6.8672199 | G28: =G8*365/'Profit & Loss Statement'!G$5 -> 10.714876 | H28: =H8*365/'Profit & Loss Statement'!H$5 -> 8.0206908 | I28: =I8*365/'Revenue Model'!I$3 -> 8.7970717 | J28: =I28*50%+H28*30%+G28*10%+F28*10% -> 8.5629527 | K28: =J28*50%+I28*30%+H28*10%+G28*10% -> 8.7941546 | L28: =K28*50%+J28*30%+I28*10%+H28*10% -> 8.6477393 | M28: =L28*50%+K28*30%+J28*10%+I28*10% -> 8.6981185 | N28: =M28*50%+L28*30%+K28*10%+J28*10% -> 8.6790918
B29: Other assets | C29: =C9*365/'Profit & Loss Statement'!C$5 -> 11.115246 | D29: =D9*365/'Profit & Loss Statement'!D$5 -> 5.32946 | E29: =E9*365/'Profit & Loss Statement'!E$5 -> 6.392083 | F29: =F9*365/'Profit & Loss Statement'!F$5 -> 4.9688797 | G29: =G9*365/'Profit & Loss Statement'!G$5 -> 6.0371901 | H29: =H9*365/'Profit & Loss Statement'!H$5 -> 4.8087155 | I29: =I9*365/'Revenue Model'!I$3 -> 6.4530728 | J29: =I29*40%+H29*30%+G29*10%+F29*10%+E29*10% -> 5.763659 | K29: =J29*40%+I29*30%+H29*10%+G29*10%+F29*10% -> 5.822864 | L29: =K29*40%+J29*30%+I29*10%+H29*10%+G29*10% -> 5.7881411 | M29: =L29*40%+K29*30%+J29*10%+I29*10%+H29*10% -> 5.7646604 | N29: =M29*40%+L29*30%+K29*10%+J29*10%+I29*10% -> 5.8462661
B30: Current Liabilities as days of sales | C30: =C23 -> FY18 | D30: =D23 -> FY19 | E30: =E23 -> FY20 | F30: =F23 -> FY21 | G30: =G23 -> FY22 | H30: =H23 -> FY23 | I30: =I23 -> FY24 | J30: =J23 -> FY25E | ... N30: =N23 -> FY29E
B31: Outstanding Dues of creditors & Enterprises | C31: =C12*365/'Profit & Loss Statement'!C$5 -> 4.2696906 | D31: =D12*365/'Profit & Loss Statement'!D$5 -> 6.596907 | E31: =E12*365/'Profit & Loss Statement'!E$5 -> 36.181602 | F31: =F12*365/'Profit & Loss Statement'!F$5 -> 52.738589 | G31: =G12*365/'Profit & Loss Statement'!G$5 -> 40.35124 | H31: =H12*365/'Profit & Loss Statement'!H$5 -> 42.153323 | I31: =I12*365/'Profit & Loss Statement'!I$5 -> 43.710048 | J31: =I31*40%+H31*30%+G31*10%+F31*10%+E31*10% -> 43.057159 | K31: =J31*40%+I31*30%+H31*10%+G31*10%+F31*10% -> 43.860193 | L31: =K31*40%+J31*30%+I31*10%+H31*10%+G31*10% -> 43.082686 | M31: =L31*40%+K31*30%+J31*10%+I31*10%+H31*10% -> 43.283186 | N31: =M31*40%+L31*30%+K31*10%+J31*10%+I31*10% -> 43.30082
B32: Financial Liabilities
B33: i. Borrowings | C33: =C14*365/'Profit & Loss Statement'!C$5 -> 53.507731 | D33: =D14*365/'Profit & Loss Statement'!D$5 -> 37.170201 | E33: =E14*365/'Profit & Loss Statement'!E$5 -> 0.51136664 | F33: =F14*365/'Profit & Loss Statement'!F$5 -> 2.5363071 | G33: =G14*365/'Profit & Loss Statement'!G$5 -> 1.5785124 | H33: =H14*365/'Profit & Loss Statement'!H$5 -> 3.7483321 | I33: =I14*365/'Profit & Loss Statement'!I$5 -> 0.084908853 | J33: =I33*40%+H33*30%+G33*10%+F33*10%+E33*10% -> 1.6210818 | K33: =J33*40%+I33*30%+H33*10%+G33*10%+F33*10% -> 1.4602205 | L33: =K33*40%+J33*30%+I33*10%+H33*10%+G33*10% -> 1.6115881 | M33: =L33*40%+K33*30%+J33*10%+I33*10%+H33*10% -> 1.6281337 | N33: =M33*40%+L33*30%+K33*10%+J33*10%+I33*10% -> 1.451351
B34: ii. Lease Liabilities | C34: =C15*365/'Profit & Loss Statement'!C$5 -> 11.365026 | D34: =D15*365/'Profit & Loss Statement'!D$5 -> 9.7809811 | E34: =E15*365/'Profit & Loss Statement'!E$5 -> 0.048242136 | F34: =F15*365/'Profit & Loss Statement'!F$5 -> 0.038381743 | G34: =G15*365/'Profit & Loss Statement'!G$5 -> 0.033057851 | H34: =H15*365/'Profit & Loss Statement'!H$5 -> 0.021577569 | I34: =I15*365/'Profit & Loss Statement'!I$5 -> 0.04631392 | J34: =I34*40%+H34*30%+G34*10%+F34*10%+E34*10% -> 0.036967012 | K34: =J34*40%+I34*30%+H34*10%+G34*10%+F34*10% -> 0.037982697 | L34: =K34*40%+J34*30%+I34*10%+H34*10%+G34*10% -> 0.036378116 | M34: =L34*40%+K34*30%+J34*10%+I34*10%+H34*10% -> 0.036431906 | N34: =M34*40%+L34*30%+K34*10%+J34*10%+I34*10% -> 0.03761256
B35: iii. Trade payables | C35: =C16*365/'Profit & Loss Statement'!C$5 -> 19.498514 | D35: =D16*365/'Profit & Loss Statement'!D$5 -> 17.793719 | E35: =E16*365/'Profit & Loss Statement'!E$5 -> 0 | F35: =F16*365/'Profit & Loss Statement'!F$5 -> 0 | G35: =G16*365/'Profit & Loss Statement'!G$5 -> 0 | H35: =H16*365/'Profit & Loss Statement'!H$5 -> 0 | I35: =I16*365/'Profit & Loss Statement'!I$5 -> 0 | J35: =I35*40%+H35*30%+G35*10%+F35*10%+E35*10% -> 0 | K35: =J35*40%+I35*30%+H35*10%+G35*10%+F35*10% -> 0 | L35: =K35*40%+J35*30%+I35*10%+H35*10%+G35*10% -> 0 | M35: =L35*40%+K35*30%+J35*10%+I35*10%+H35*10% -> 0 | N35: =M35*40%+L35*30%+K35*10%+J35*10%+I35*10% -> 0
B36: iv. Other Financial liabilities | C36: =C17*365/'Profit & Loss Statement'!C$5 -> 234.23195 | D36: =D17*365/'Profit & Loss Statement'!D$5 -> 185.04726 | E36: =E17*365/'Profit & Loss Statement'!E$5 -> 4.3610891 | F36: =F17*365/'Profit & Loss Statement'!F$5 -> 6.5975104 | G36: =G17*365/'Profit & Loss Statement'!G$5 -> 8.3760331 | H36: =H17*365/'Profit & Loss Statement'!H$5 -> 7.0589477 | I36: =I17*365/'Profit & Loss Statement'!I$5 -> 5.7223421 | J36: =I36*40%+H36*30%+G36*10%+F36*10%+E36*10% -> 6.3400844 | K36: =J36*40%+I36*30%+H36*10%+G36*10%+F36*10% -> 6.4559855 | L36: =K36*40%+J36*30%+I36*10%+H36*10%+G36*10% -> 6.6001518 | M36: =L36*40%+K36*30%+J36*10%+I36*10%+H36*10% -> 6.4889938 | N36: =M36*40%+L36*30%+K36*10%+J36*10%+I36*10% -> 6.4274842
B37: Provisions | C37: =C18*365/'Profit & Loss Statement'!C$5 -> 6.400633 | D37: =D18*365/'Profit & Loss Statement'!D$5 -> 6.1703029 | E37: =E18*365/'Profit & Loss Statement'!E$5 -> 3.2852895 | F37: =F18*365/'Profit & Loss Statement'!F$5 -> 3.8537344 | G37: =G18*365/'Profit & Loss Statement'!G$5 -> 3.5578512 | H37: =H18*365/'Profit & Loss Statement'!H$5 -> 3.3383582 | I37: =I18*365/'Profit & Loss Statement'!I$5 -> 3.3757701 | J37: =I37*40%+H37*30%+G37*10%+F37*10%+E37*10% -> 3.421503 | K37: =J37*40%+I37*30%+H37*10%+G37*10%+F37*10% -> 3.4563267 | L37: =K37*40%+J37*30%+I37*10%+H37*10%+G37*10% -> 3.4361795 | M37: =L37*40%+K37*30%+J37*10%+I37*10%+H37*10% -> 3.424933 | N37: =M37*40%+L37*30%+K37*10%+J37*10%+I37*10% -> 3.426187
B38: Other current liabilities | C38: =C19*365/'Profit & Loss Statement'!C$5 -> 5.2375912 | D38: =D19*365/'Profit & Loss Statement'!D$5 -> 4.5504438 | E38: =E19*365/'Profit & Loss Statement'!E$5 -> 6.7973169 | F38: =F19*365/'Profit & Loss Statement'!F$5 -> 13.900415 | G38: =G19*365/'Profit & Loss Statement'!G$5 -> 11.855372 | H38: =H19*365/'Profit & Loss Statement'!H$5 -> 10.286336 | I38: =I19*365/'Profit & Loss Statement'!I$5 -> 10.742256 | J38: =I38*40%+H38*30%+G38*10%+F38*10%+E38*10% -> 10.638114 | K38: =J38*40%+I38*30%+H38*10%+G38*10%+F38*10% -> 11.082135 | L38: =K38*40%+J38*30%+I38*10%+H38*10%+G38*10% -> 10.912684 | M38: =L38*40%+K38*30%+J38*10%+I38*10%+H38*10% -> 10.856385 | N38: =M38*40%+L38*30%+K38*10%+J38*10%+I38*10% -> 10.86261
B41: Debt Schedule | C41: =C30 -> FY18 | D41: =D30 -> FY19 | E41: =E30 -> FY20 | F41: =F30 -> FY21 | G41: =G30 -> FY22 | H41: =H30 -> FY23 | I41: =I30 -> FY24 | J41: =J30 -> FY25E | ... N41: =N30 -> FY29E
A42: B/S | B42: Long term Borrowings | C42: ='Balance Sheet'!C41 -> 1483 | D42: ='Balance Sheet'!D41 -> 850 | E42: ='Balance Sheet'!E41 -> 5 | F42: ='Balance Sheet'!F41 -> 2.8 | G42: ='Balance Sheet'!G41 -> 0 | H42: ='Balance Sheet'!H41 -> 0 | I42: ='Balance Sheet'!I41 -> 0 | J42: =AVERAGE(E42:I42)/AVERAGE(E$44:I$44)*J$44 -> 0.12099114 | K42: =AVERAGE(F42:J42)/AVERAGE(F$44:J$44)*K$44 -> 0.049258597 | L42: =AVERAGE(G42:K42)/AVERAGE(G$44:K$44)*L$44 -> 0.0038212058 | M42: =AVERAGE(H42:L42)/AVERAGE(H$44:L$44)*M$44 -> 0.005140706 | N42: =AVERAGE(I42:M42)/AVERAGE(I$44:M$44)*N$44 -> 0.041393374
A43: B/S | B43: Short Term Borrowing | C43: ='Balance Sheet'!C50 -> 6855 | D43: ='Balance Sheet'!D50 -> 6012 | E43: ='Balance Sheet'!E50 -> 106 | F43: ='Balance Sheet'!F50 -> 489 | G43: ='Balance Sheet'!G50 -> 382 | H43: ='Balance Sheet'!H50 -> 1216 | I43: ='Balance Sheet'!I50 -> 33 | J43: =AVERAGE(E43:I43)/AVERAGE(E$44:I$44)*J$44 -> 34.529009 | K43: =AVERAGE(F43:J43)/AVERAGE(F$44:J$44)*K$44 -> 36.333241 | L43: =AVERAGE(G43:K43)/AVERAGE(G$44:K$44)*L$44 -> 38.197804 | M43: =AVERAGE(H43:L43)/AVERAGE(H$44:L$44)*M$44 -> 40.106566 | N43: =AVERAGE(I43:M43)/AVERAGE(I$44:M$44)*N$44 -> 42.075898 | P43: Total Debt | Q43: 2 | R43: B/L Sheet
B44: Total Borrowings | C44: =SUM(C42:C43) -> 8338 | D44: =SUM(D42:D43) -> 6862 | E44: =SUM(E42:E43) -> 111 | F44: =SUM(F42:F43) -> 491.8 | G44: =SUM(G42:G43) -> 382 | H44: =SUM(H42:H43) -> 1216 | I44: =SUM(I42:I43) -> 33 | J44: =I44+J60 -> 34.65 | K44: =J44+K60 -> 36.3825 | L44: =K44+L60 -> 38.201625 | M44: =L44+M60 -> 40.111706 | N44: =M44+N60 -> 42.117292 | P44: Total Lease | Q44: 2 | R44: B/L Sheet
P45: Finance Cost | Q45: 1 | R45: I/S
A46: B/S | B46: Long Term Lease | C46: ='Balance Sheet'!C42 -> 4314 | D46: ='Balance Sheet'!D42 -> 2964 | E46: ='Balance Sheet'!E42 -> 60 | F46: ='Balance Sheet'!F42 -> 39 | G46: ='Balance Sheet'!G42 -> 33 | H46: ='Balance Sheet'!H42 -> 25 | I46: ='Balance Sheet'!I42 -> 67 | J46: =AVERAGE(E46:I46)/AVERAGE(E$48:I$48)*J$48 -> 72.857143 | K46: =AVERAGE(F46:J46)/AVERAGE(F$48:J$48)*K$48 -> 75.5882 | L46: =AVERAGE(G46:K46)/AVERAGE(G$48:K$48)*L$48 -> 78.913397 | M46: =AVERAGE(H46:L46)/AVERAGE(H$48:L$48)*M$48 -> 82.828257 | N46: =AVERAGE(I46:M46)/AVERAGE(I$48:M$48)*N$48 -> 87.12069
A47: B/S | B47: Short Term Lease | C47: ='Balance Sheet'!C51 -> 1456 | D47: ='Balance Sheet'!D51 -> 1582 | E47: ='Balance Sheet'!E51 -> 10 | F47: ='Balance Sheet'!F51 -> 7.4 | G47: ='Balance Sheet'!G51 -> 8 | H47: ='Balance Sheet'!H51 -> 7 | I47: ='Balance Sheet'!I51 -> 18 | J47: =AVERAGE(E47:I47)/AVERAGE(E$48:I$48)*J$48 -> 16.392857 | K47: =AVERAGE(F47:J47)/AVERAGE(F$48:J$48)*K$48 -> 18.1243 | L47: =AVERAGE(G47:K47)/AVERAGE(G$48:K$48)*L$48 -> 19.484728 | M47: =AVERAGE(H47:L47)/AVERAGE(H$48:L$48)*M$48 -> 20.489774 | N47: =AVERAGE(I47:M47)/AVERAGE(I$48:M$48)*N$48 -> 21.363242
B48: Total Lease | C48: =SUM(C46:C47) -> 5770 | D48: =SUM(D46:D47) -> 4546 | E48: =SUM(E46:E47) -> 70 | F48: =SUM(F46:F47) -> 46.4 | G48: =SUM(G46:G47) -> 41 | H48: =SUM(H46:H47) -> 32 | I48: =SUM(I46:I47) -> 85 | J48: =I48+J65 -> 89.25 | K48: =J48+K65 -> 93.7125 | L48: =K48+L65 -> 98.398125 | M48: =L48+M65 -> 103.31803 | N48: =M48+N65 -> 108.48393
P49: Annual Report
B50: Cost on Borrowings | D50: 576 | E50: 34 | F50: 25 | G50: 12 | H50: 32.5 | I50: 35 | J50: =J55*AVERAGE(I44:J44) -> 1.8957166 | K50: =K55*AVERAGE(J44:K44) -> 1.9905024 | L50: =L55*AVERAGE(K44:L44) -> 2.0900275 | M50: =M55*AVERAGE(L44:M44) -> 2.1945289 | N50: =N55*AVERAGE(M44:N44) -> 2.3042553
B51: Cost on Lease Liabilities | D51: 549 | E51: 48 | F51: 59 | G51: 58 | H51: 65 | I51: 75 | J51: =J56*AVERAGE(I48:J48) -> 133.42641 | K51: =K56*AVERAGE(J48:K48) -> 128.69069 | L51: =L56*AVERAGE(K48:L48) -> 141.11393 | M51: =M56*AVERAGE(L48:M48) -> 145.02556 | N51: =N56*AVERAGE(M48:N48) -> 153.92747 | P51: Forecast this debt schedule
B52: Unwinding of Interest | D52: 469 | E52: 52 | F52: 18 | G52: 57 | H52: 154.5 | I52: 84 | J52: =AVERAGE(E52:I52) -> 73.1 | K52: =AVERAGE(F52:J52) -> 77.32 | L52: =AVERAGE(G52:K52) -> 89.184 | M52: =AVERAGE(H52:L52) -> 95.6208 | N52: =AVERAGE(I52:M52) -> 83.84496 | P52: Steps to build the debt schedule:
A53: I/S | B53: Total Finance cost | D53: =SUM(D50:D52) -> 1594 | E53: =SUM(E50:E52) -> 134 | F53: =SUM(F50:F52) -> 102 | G53: =SUM(G50:G52) -> 127 | H53: =SUM(H50:H52) -> 252 | I53: =SUM(I50:I52) -> 194 | J53: =SUM(J50:J52) -> 208.42213 | K53: =SUM(K50:K52) -> 208.0012 | ... N53: =SUM(N50:N52) -> 240.07668 | P53: 1. Forecast the Int Rate
P54: 2. Forecast the debt
B55: Cost of Borrowing (%) | D55: =D50/C44 -> 0.069081314 | E55: =E50/AVERAGE(D44:E44) -> 0.0097519002 | F55: =F50/AVERAGE(E44:F44) -> 0.082946251 | G55: =G50/AVERAGE(F44:G44) -> 0.027466239 | H55: =H50/AVERAGE(G44:H44) -> 0.040675845 | I55: =I50/AVERAGE(H44:I44) -> 0.056044836 | J55: =AVERAGE(I55) -> 0.056044836 | K55: =AVERAGE(I55:J55) -> 0.056044836 | L55: =AVERAGE(J55:K55) -> 0.056044836 | M55: =AVERAGE(K55:L55) -> 0.056044836 | N55: =AVERAGE(L55:M55) -> 0.056044836 | P55: 3. Calculate the interest expense (Debt x Int Rate)
B56: Cost Of Lease (%) | D56: =D51/C48 -> 0.095147314 | E56: =E51/AVERAGE(D48:E48) -> 0.020797227 | F56: =F51/AVERAGE(E48:F48) -> 1.0137457 | G56: =G51/AVERAGE(F48:G48) -> 1.3272311 | H56: =H51/AVERAGE(G48:H48) -> 1.7808219 | I56: =I51/AVERAGE(H48:I48) -> 1.2820513 | J56: =AVERAGE(H56:I56) -> 1.5314366 | K56: =AVERAGE(I56:J56) -> 1.4067439 | L56: =AVERAGE(J56:K56) -> 1.4690903 | M56: =AVERAGE(K56:L56) -> 1.4379171 | N56: =AVERAGE(L56:M56) -> 1.4535037
B57: Weighted Average Cost Of Borrowing
B58: New Borrowing Raised | I58: 0.1
B59: Exsisting Borrowing Repaid | I59: 0.05
B60: Net Borrowing Raised | I60: =I58-I59 -> 0.05 | J60: =I44*5% -> 1.65 | K60: =J44*5% -> 1.7325 | L60: =K44*5% -> 1.819125 | M60: =L44*5% -> 1.9100813 | N60: =M44*5% -> 2.0055853
B61: Net Borrowing Added to Long Term Borrowings | J61: =J42-I42 -> 0.12099114 | K61: =K42-J42 -> -0.071732539 | L61: =L42-K42 -> -0.045437391 | M61: =M42-L42 -> 0.0013195002 | N61: =N42-M42 -> 0.036252667
B63: New Lease added
B64: Existing lease removed
B65: Net Lease added | J65: =I48*5% -> 4.25 | K65: =J48*5% -> 4.4625 | L65: =K48*5% -> 4.685625 | M65: =L48*5% -> 4.9199063 | N65: =M48*5% -> 5.1659016
B66: Net Lease added to long term lease | J66: =J46-I46 -> 5.8571429 | K66: =K46-J46 -> 2.7310574 | L66: =L46-K46 -> 3.3251965 | M66: =M46-L46 -> 3.9148603 | N66: =N46-M46 -> 4.2924334
B70: Capex Schedule | C70: =C41 -> FY18 | D70: =D41 -> FY19 | E70: =E41 -> FY20 | F70: =F41 -> FY21 | G70: =G41 -> FY22 | H70: =H41 -> FY23 | I70: =I41 -> FY24 | J70: =J41 -> FY25E | ... N70: =N41 -> FY29E
A71: B/S | B71: Property, Plant & Equipment | C71: ='Balance Sheet'!C5 -> 264 | D71: ='Balance Sheet'!D5 -> 214 | E71: ='Balance Sheet'!E5 -> 14790 | F71: ='Balance Sheet'!F5 -> 14178 | G71: ='Balance Sheet'!G5 -> 12826 | H71: ='Balance Sheet'!H5 -> 26803 | I71: ='Balance Sheet'!I5 -> 26798 | J71: =J78 -> 28150.664 | K71: =K78 -> 30751.19 | L71: =L78 -> 32972.031 | M71: =M78 -> 35918.426 | N71: =N78 -> 39023.19
A72: B/S | B72: Intangible Assets | C72: ='Balance Sheet'!C8 -> 793 | D72: ='Balance Sheet'!D8 -> 196 | E72: ='Balance Sheet'!E8 -> 336 | F72: ='Balance Sheet'!F8 -> 224 | G72: ='Balance Sheet'!G8 -> 350 | H72: ='Balance Sheet'!H8 -> 548 | I72: ='Balance Sheet'!I8 -> 454 | J72: =J82 -> 517.97957 | K72: =K82 -> 610.12824 | L72: =L82 -> 699.64408 | M72: =M82 -> 817.77078 | N72: =N82 -> 950.083
A73: B/S | B73: Right-of-use Assets | C73: ='Balance Sheet'!C10 -> 5484 | D73: ='Balance Sheet'!D10 -> 3965 | E73: ='Balance Sheet'!E10 -> 618 | F73: ='Balance Sheet'!F10 -> 586 | G73: ='Balance Sheet'!G10 -> 571 | H73: ='Balance Sheet'!H10 -> 591 | I73: ='Balance Sheet'!I10 -> 613 | J73: =J86 -> 626.96075 | K73: =K86 -> 637.3457 | L73: =L86 -> 645.69404 | M73: =M86 -> 655.31396 | N73: =N86 -> 664.29856 | P73: The Treatment of right of use of assets will be bit different vs PPE and intangible assets.
B75: Property, Plant & Equipment
B76: Gross Long Term Assets: | C76: 264 | D76: 357 | E76: 28213 | F76: 29943 | G76: 30705 | H76: 53725 | I76: 58264 | J76: =I76+J99 -> 65789.5 | K76: =J76+K99 -> 75048.754 | L76: =K76+L99 -> 85036.845 | M76: =L76+M99 -> 96687.721 | N76: =M76+N99 -> 109744.44
B77: Accumulated Depreciation: | D77: 143 | E77: 13423 | F77: 15765 | G77: 17879 | H77: 26922 | I77: 31466 | J77: =I77+J88 -> 37638.836 | K77: =J77+K88 -> 44297.563 | L77: =K77+L88 -> 52064.814 | M77: =L77+M88 -> 60769.295 | N77: =M77+N88 -> 70721.251
B78: Net PPE | C78: =C76-C77 -> 264 | D78: =D76-D77 -> 214 | E78: =E76-E77 -> 14790 | F78: =F76-F77 -> 14178 | G78: =G76-G77 -> 12826 | H78: =H76-H77 -> 26803 | I78: =I76-I77 -> 26798 | J78: =J76-J77 -> 28150.664 | ... N78: =N76-N77 -> 39023.19
B79: Intangible Assets
B80: Gross Long Term Assets: | C80: =29+545+39+180 -> 793 | D80: =32+577+42+187 -> 838 | E80: 937 | F80: 967 | G80: 1254 | H80: 1660 | I80: 1783 | J80: =I80+J102 -> 2108.5 | K80: =J80+K102 -> 2500.7806 | L80: =K80+L102 -> 2950.9786 | M80: =L80+M102 -> 3492.0018 | N80: =M80+N102 -> 4126.3465
B81: Accumulated Depreciation: | D81: =32+468+36+106 -> 642 | E81: 601 | F81: 743 | G81: 904 | H81: 1112 | I81: 1329 | J81: =I81+J90 -> 1590.5204 | K81: =J81+K90 -> 1890.6524 | L81: =K81+L90 -> 2251.3345 | M81: =L81+M90 -> 2674.231 | N81: =M81+N90 -> 3176.2635
B82: Net Intangible Assets | C82: =C80-C81 -> 793 | D82: =D80-D81 -> 196 | E82: =E80-E81 -> 336 | F82: =F80-F81 -> 224 | G82: =G80-G81 -> 350 | H82: =H80-H81 -> 548 | I82: =I80-I81 -> 454 | J82: =J80-J81 -> 517.97957 | ... N82: =N80-N81 -> 950.083
B83: Right-of-use Assets
B84: Gross Long Term Assets: | C84: 5484 | D84: =5484+255-71 -> 5668 | E84: 639 | F84: 606 | G84: 700 | H84: 698 | I84: 741 | J84: =I86+J105 -> 646 | K84: =J86+K105 -> 655.51962 | L84: =K86+L105 -> 664.60658 | M84: =L86+M105 -> 674.06286 | N84: =M86+N105 -> 683.4373
B85: Depreciation: | C85: 0 | D85: 1703 | E85: 21 | F85: 20 | G85: 129 | H85: 107 | I85: 128 | J85: =J92 -> 19.039246 | K85: =K92 -> 18.173924 | L85: =L92 -> 18.912541 | M85: =M92 -> 18.748894 | N85: =N92 -> 19.138739
B86: Net Right of use assets | C86: =C84-C85 -> 5484 | D86: =D84-D85 -> 3965 | E86: =E84-E85 -> 618 | F86: =F84-F85 -> 586 | G86: =G84-G85 -> 571 | H86: =H84-H85 -> 591 | I86: =I84-I85 -> 613 | J86: =J84-J85 -> 626.96075 | ... N86: =N84-N85 -> 664.29856
B88: Depreciation on PPE | D88: 143 | E88: 3362 | F88: 2872 | G88: 2611 | H88: 4620 | I88: 5017 | J88: =J89*AVERAGE(I76:J76) -> 6172.8357 | K88: =K89*AVERAGE(J76:K76) -> 6658.7275 | L88: =L89*AVERAGE(K76:L76) -> 7767.2506 | M88: =M89*AVERAGE(L76:M76) -> 8704.4806 | N88: =N89*AVERAGE(M76:N76) -> 9951.9568
B89: As a % of GLTA | D89: =D88/D76 -> 0.40056022 | E89: =E88/(AVERAGE(D76:E76)) -> 0.23535177 | F89: =F88/(AVERAGE(E76:F76)) -> 0.098768829 | G89: =G88/(AVERAGE(F76:G76)) -> 0.086103416 | H89: =H88/(AVERAGE(G76:H76)) -> 0.10943977 | I89: =I88/(AVERAGE(H76:I76)) -> 0.089598086 | J89: =AVERAGE(H89:I89) -> 0.099518929 | K89: =AVERAGE(I89:J89) -> 0.094558507 | L89: =AVERAGE(J89:K89) -> 0.097038718 | M89: =AVERAGE(K89:L89) -> 0.095798613 | N89: =AVERAGE(L89:M89) -> 0.096418665
B90: Depreciation on Intangible Asset | D90: 632 | E90: 145 | F90: 142 | G90: 161 | H90: 208 | I90: 217 | J90: =J91*AVERAGE(I80:J80) -> 261.52043 | K90: =K91*AVERAGE(J80:K80) -> 300.13197 | L90: =L91*AVERAGE(K80:L80) -> 360.68212 | M90: =M91*AVERAGE(L80:M80) -> 422.89648 | N90: =N91*AVERAGE(M80:N80) -> 502.0325
B91: As a % of GLTA | D91: =D90/D80 -> 0.75417661 | E91: =E90/AVERAGE(D80:E80) -> 0.16338028 | F91: =F90/AVERAGE(E80:F80) -> 0.14915966 | G91: =G90/AVERAGE(F80:G80) -> 0.14497974 | H91: =H90/AVERAGE(G80:H80) -> 0.14275909 | I91: =I90/AVERAGE(H80:I80) -> 0.12605286 | J91: =AVERAGE(H91:I91) -> 0.13440598 | K91: =AVERAGE(I91:J91) -> 0.13022942 | L91: =AVERAGE(J91:K91) -> 0.1323177 | M91: =AVERAGE(K91:L91) -> 0.13127356 | N91: =AVERAGE(L91:M91) -> 0.13179563
B92: Depreciation on Right of use Assets | D92: 1703 | E92: 21 | F92: 20 | G92: 17 | H92: 18 | I92: 22 | J92: =J93*AVERAGE(I84:J84) -> 19.039246 | K92: =K93*AVERAGE(J84:K84) -> 18.173924 | L92: =L93*AVERAGE(K84:L84) -> 18.912541 | M92: =M93*AVERAGE(L84:M84) -> 18.748894 | N92: =N93*AVERAGE(M84:N84) -> 19.138739
B93: As a % of GLTA | D93: =D92/D84 -> 0.30045872 | E93: =E92/AVERAGE(D84:E84) -> 0.0066592675 | F93: =F92/AVERAGE(E84:F84) -> 0.032128514 | G93: =G92/AVERAGE(F84:G84) -> 0.026033691 | H93: =H92/AVERAGE(G84:H84) -> 0.025751073 | I93: =I92/AVERAGE(H84:I84) -> 0.030576789 | J93: =AVERAGE(G93:I93) -> 0.027453851 | K93: =AVERAGE(H93:J93) -> 0.027927238 | L93: =AVERAGE(I93:K93) -> 0.028652626 | M93: =AVERAGE(J93:L93) -> 0.028011238 | N93: =AVERAGE(K93:M93) -> 0.028197034
A94: I/S | B94: Total Depreciation | C94: =C88+C90+C92 -> 0 | D94: =D88+D90+D92 -> 2478 | E94: =E88+E90+E92 -> 3528 | F94: =F88+F90+F92 -> 3034 | G94: =G88+G90+G92 -> 2789 | H94: =H88+H90+H92 -> 4846 | I94: =I88+I90+I92 -> 5256 | J94: =J92+J90+J88 -> 6453.3954 | K94: =K92+K90+K88 -> 6977.0334 | L94: =L92+L90+L88 -> 8146.8453 | M94: =M92+M90+M88 -> 9146.126 | N94: =N92+N90+N88 -> 10473.128
B95: Growth Capex (Assumed %) | J95: 0.5 | K95: 0.5 | L95: 0.5 | M95: 0.5 | N95: 0.5
B97: Maintenance Capex on PPE | J97: =I88 -> 5017 | K97: =J88 -> 6172.8357 | L97: =K88 -> 6658.7275 | M97: =L88 -> 7767.2506 | N97: =M88 -> 8704.4806
B98: Growth Capex On PPE | J98: =J97*J95 -> 2508.5 | K98: =K97*K95 -> 3086.4179 | L98: =L97*L95 -> 3329.3638 | M98: =M97*M95 -> 3883.6253 | N98: =N97*N95 -> 4352.2403
B99: Total Capex On PPE | J99: =J97+J98 -> 7525.5 | K99: =K97+K98 -> 9259.2536 | L99: =L97+L98 -> 9988.0913 | M99: =M97+M98 -> 11650.876 | N99: =N97+N98 -> 13056.721
B100: Maintenance Capex on Intangible Assets | J100: =I90 -> 217 | K100: =J90 -> 261.52043 | L100: =K90 -> 300.13197 | M100: =L90 -> 360.68212 | N100: =M90 -> 422.89648
B101: Growth Capex On Intangible Assets | J101: =J100*J95 -> 108.5 | K101: =K100*K95 -> 130.76022 | L101: =L100*L95 -> 150.06599 | M101: =M100*M95 -> 180.34106 | N101: =N100*N95 -> 211.44824
B102: Total Capex On Intangible Assets | J102: =J100+J101 -> 325.5 | K102: =K100+K101 -> 392.28065 | L102: =L100+L101 -> 450.19796 | M102: =M100+M101 -> 541.02318 | N102: =N100+N101 -> 634.34472
B103: Maintenance Capex on Right of Use of Assets | J103: =I92 -> 22 | K103: =J92 -> 19.039246 | L103: =K92 -> 18.173924 | M103: =L92 -> 18.912541 | N103: =M92 -> 18.748894
B104: Growth Capex On Right of Use of Assets | J104: =J103*J95 -> 11 | K104: =K103*K95 -> 9.5196228 | L104: =L103*L95 -> 9.086962 | M104: =M103*M95 -> 9.4562707 | N104: =N103*N95 -> 9.3744472
B105: Total Capex On Right of use of Assets | J105: =J103+J104 -> 33 | K105: =K103+K104 -> 28.558869 | L105: =L103+L104 -> 27.260886 | M105: =M103+M104 -> 28.368812 | N105: =N103+N104 -> 28.123342
B106: Total Capex | J106: =J99+J102+J105 -> 7884 | K106: =K99+K102+K105 -> 9680.0931 | L106: =L99+L102+L105 -> 10465.55 | M106: =M99+M102+M105 -> 12220.268 | N106: =N99+N102+N105 -> 13719.189
B109: Master Equations: | F109: If you are trying to calculate % of I/S item wrt to B/S always use last two years average.
A110: 1 | B110: GLTA(25E) = GLTA(24E) + CapEx (25)
A111: 2 | B111: Acc Dep(25E) = Acc Dep (24E) + Deprn Exp (25E)
A112: 3 | B112: CapEx (25E) = Maint Capex (25E) + Growth CapEx (25E)
...

Sheet Profit & Loss Statement
B1: Profit & Loss Statement ( All Amount in ₹ cr, unless otherwise stated)
B3: P&L Statement | C3: ='Balance Sheet'!C3 -> FY18 | D3: ='Balance Sheet'!D3 -> FY19 | E3: ='Balance Sheet'!E3 -> FY20 | F3: ='Balance Sheet'!F3 -> FY21 | G3: ='Balance Sheet'!G3 -> FY22 | H3: ='Balance Sheet'!H3 -> FY23 | I3: ='Balance Sheet'!I3 -> FY24 | J3: ='Balance Sheet'!J3 -> FY25E | ... N3: ='Balance Sheet'!N3 -> FY29E
B4: Income
B5: Revenue from Operations | C5: 46761 | D5: 59036 | E5: 75660 | F5: 70372 | G5: 88330 | H5: 118410 | I5: 141858 | J5: ='Revenue Model'!J3 -> 145471.7 | K5: ='Revenue Model'!K3 -> 145107.7 | L5: ='Revenue Model'!L3 -> 144984.7 | M5: ='Revenue Model'!M3 -> 146605.35 | N5: ='Revenue Model'!N3 -> 149869.7
B6: Other Income | C6: 1672 | D6: 1145 | E6: 3334 | F6: 2936 | G6: 1745 | H6: 2265 | I6: 4094 | J6: =Assumptions!J4 -> 4743.1466 | K6: =Assumptions!K4 -> 4317.6636 | L6: =Assumptions!L4 -> 4006.0408 | M6: =Assumptions!M4 -> 4190.8343 | N6: =Assumptions!N4 -> 4463.6282
B7: Total Income | C7: =SUM(C5:C6) -> 48433 | D7: =SUM(D5:D6) -> 60181 | E7: =SUM(E5:E6) -> 78994 | F7: =SUM(F5:F6) -> 73308 | G7: =SUM(G5:G6) -> 90075 | H7: =SUM(H5:H6) -> 120675 | I7: =SUM(I5:I6) -> 145952 | J7: =SUM(J5:J6) -> 150214.85 | ... N7: =SUM(N5:N6) -> 154333.33
B9: Expense
B10: Selling, General & Administrative Expenses | C10: 35254 | D10: 38505 | E10: 8456 | F10: 8208 | G10: 9437 | H10: 10316 | I10: 12083 | J10: =Assumptions!J9 -> 13403.71 | K10: =Assumptions!K9 -> 14868.779 | L10: =Assumptions!L9 -> 16493.984 | M10: =Assumptions!M9 -> 18296.829 | N10: =Assumptions!N9 -> 20296.731
B11: Depreciation and amortisation | C11: 687 | D11: 2478 | E11: 3528 | F11: 3034 | G11: 2789 | H11: 4846 | I11: 5256 | J11: =Schedules_Populated!J94 -> 6453.3954 | K11: =Schedules_Populated!K94 -> 6977.0334 | L11: =Schedules_Populated!L94 -> 8146.8453 | M11: =Schedules_Populated!M94 -> 9146.126 | N11: =Schedules_Populated!N94 -> 10473.128 | P11: 3rd Linkage
B12: Finance Cost | E12: 134 | F12: 102 | G12: 127 | H12: 252 | I12: 194 | J12: =Schedules_Populated!J53 -> 208.42213 | K12: =Schedules_Populated!K53 -> 208.0012 | L12: =Schedules_Populated!L53 -> 232.38795 | M12: =Schedules_Populated!M53 -> 242.84088 | N12: =Schedules_Populated!N53 -> 240.07668
B13: Total Operating Expenses | C13: =13527+335 -> 13862 | D13: 15048 | E13: =63554-134 -> 63420 | F13: =59948-102 -> 59846 | G13: =76103-127 -> 75976 | H13: =100098-252 -> 99846 | I13: =116699-194 -> 116505 | J13: =Assumptions!J13-208 -> 131387.58 | K13: =Assumptions!K13-208 -> 132129.54 | L13: =Assumptions!L13-232 -> 134530.1 | M13: =Assumptions!M13-243 -> 134387.6 | N13: =Assumptions!N13-240 -> 135386.49
B14: Total Expense | C14: =SUM(C10:C13) -> 49803 | D14: =SUM(D10:D13) -> 56031 | E14: =SUM(E10:E13) -> 75538 | F14: =SUM(F10:F13) -> 71190 | G14: =SUM(G10:G13) -> 88329 | H14: =SUM(H10:H13) -> 115260 | I14: =SUM(I10:I13) -> 134038 | J14: =SUM(J10:J13) -> 151453.11 | ... N14: =SUM(N10:N13) -> 166396.42
B16: EBIT | C16: =C7-C14 -> -1370 | D16: =D7-D14 -> 4150 | E16: 7237 | F16: 5423 | G16: 4824 | H16: 10691 | I16: 17618 | J16: 26427 | K16: 38055 | L16: 51755 | M16: 67281 | N16: 84774 | P16: Capex Schedule
B17: Interest | C17: 0 | D17: 1258 | E17: =E12 -> 134 | F17: =F12 -> 102 | G17: =G12 -> 127 | H17: =H12 -> 252 | I17: =I12 -> 194 | J17: =J12 -> 208.42213 | K17: =K12 -> 208.0012 | L17: =L12 -> 232.38795 | ... N17: =N12 -> 240.07668 | P17: The linkage b/w I/S and B/S through deprn and amortization
B18: Profit before tax | C18: =C16-C17 -> -1370 | D18: =D16-D17 -> 2892 | E18: =E16-E17 -> 7103 | F18: =F16-F17 -> 5321 | G18: =G16-G17 -> 4697 | H18: =H16-H17 -> 10439 | I18: =I16-I17 -> 17424 | J18: =J16-J17 -> 26218.578 | ... N18: =N16-N17 -> 84533.923
B20: Tax expense
B21: Current tax | C21: 0 | D21: 0 | E21: 1376 | F21: 1156 | G21: 1431 | H21: 2249 | I21: 3663
B22: Adjustment of tax relating to earlier periods | C22: 0 | D22: 0 | E22: =0 -> 0 | F22: 0 | G22: 0 | H22: 0 | I22: 0
B23: Deferred tax charge/credit | C23: 0 | D23: -123 | E23: 48 | F23: -224 | G23: -613 | H23: -138 | I23: -273
B24: Net Expense | C24: =SUM(C21:C23) -> 0 | D24: =SUM(D21:D23) -> -123 | E24: =SUM(E21:E23) -> 1424 | F24: =SUM(F21:F23) -> 932 | G24: =SUM(G21:G23) -> 818 | H24: =SUM(H21:H23) -> 2111 | I24: =SUM(I21:I23) -> 3390 | J24: =Assumptions!J18 -> 6599.216 | K24: =Assumptions!K18 -> 9526.0896 | L24: =Assumptions!L18 -> 12968.241 | M24: =Assumptions!M18 -> 16873.505 | N24: =Assumptions!N18 -> 21277.188
B25: Profit for the year | C25: =C18-C24 -> -1370 | D25: =D18-D24 -> 3015 | E25: =E18-E24 -> 5679 | F25: =F18-F24 -> 4389 | G25: =G18-G24 -> 3879 | H25: =H18-H24 -> 8328 | I25: =I18-I24 -> 14034 | J25: =J18-J24 -> 19619.362 | ... N25: =N18-N24 -> 63256.735
J27: 3 months | K27: 9 months
J28: =J25*3/12 -> 4904.8405 | K28: =K25*9/12 -> 21240.682
J29: Total Earning for NTM | K29: =K28+J28 -> 26145.522

Sheet Revenue Model
B1: All Amount are in ₹ cr
B2: Revenue Model | C2: =Assumptions!C2 -> FY18 | D2: =Assumptions!D2 -> FY19 | E2: =Assumptions!E2 -> FY20 | F2: =Assumptions!F2 -> FY21 | G2: =Assumptions!G2 -> FY22 | H2: =Assumptions!H2 -> FY23 | I2: =Assumptions!I2 -> FY24 | J2: =Assumptions!J2 -> FY25E | ... N2: =Assumptions!N2 -> FY29E
B3: Revenue from contracts | C3: ='Profit & Loss Statement'!C5 -> 46761 | D3: ='Profit & Loss Statement'!D5 -> 59036 | E3: ='Profit & Loss Statement'!E5 -> 75660 | F3: ='Profit & Loss Statement'!F5 -> 70372 | G3: ='Profit & Loss Statement'!G5 -> 88330 | H3: ='Profit & Loss Statement'!H5 -> 118410 | I3: ='Profit & Loss Statement'!I5 -> 141858 | J3: =J4+J6 -> 145471.7 | K3: =K4+K6 -> 145107.7 | L3: =L4+L6 -> 144984.7 | M3: =M4+M6 -> 146605.35 | N3: =N4+N6 -> 149869.7
B4: Domestic Sales | C4: =C3*C5 -> 10006.854 | D4: =D3*D5 -> 12987.92 | E4: =E3*E5 -> 70742.1 | F4: =F3*F5 -> 65727.448 | G4: =G3*G5 -> 75963.8 | H4: =H3*H5 -> 94609.59 | I4: =I3*I5 -> 122990.89 | J4: 126617 | K4: 126253 | L4: 126130 | M4: 127750.65 | N4: 131015
B5: As a percentage | C5: 0.214 | D5: 0.22 | E5: 0.935 | F5: 0.934 | G5: 0.86 | H5: 0.799 | I5: 0.867 | J5: =J4/J3 -> 0.87038922 | K5: =K4/K3 -> 0.8700641 | L5: =L4/L3 -> 0.86995386 | M5: =M4/M3 -> 0.87139146 | N5: =N4/N3 -> 0.87419272
B6: Export Sales | C6: =C3*C7 -> 36754.146 | D6: =D3*D7 -> 46048.08 | E6: =E3*E7 -> 4917.9 | F6: =F3*F7 -> 4644.552 | G6: =G3*G7 -> 12366.2 | H6: =H3*H7 -> 23800.41 | I6: =I3*I7 -> 18867.114 | J6: 18854.7 | K6: 18854.7 | L6: 18854.7 | M6: 18854.7 | N6: 18854.7
B7: As a percentage | C7: =1-C5 -> 0.786 | D7: =1-D5 -> 0.78 | E7: =1-E5 -> 0.065 | F7: =1-F5 -> 0.066 | G7: =1-G5 -> 0.14 | H7: =1-H5 -> 0.201 | I7: =1-I5 -> 0.133 | J7: =1-J5 -> 0.12961078 | ... N7: =1-N5 -> 0.12580728
B9: Sales Numbers | C9: =C2 -> FY18 | D9: =D2 -> FY19 | E9: =E2 -> FY20 | F9: =F2 -> FY21 | G9: =G2 -> FY22 | H9: =H2 -> FY23 | I9: FY24 | J9: FY25E
B10: Domestic | C10: 105 | D10: 132 | E10: 1461126 | F10: 1361722 | G10: 1414277 | H10: 1571015 | I10: 1852256 | J10: =AVERAGE(E10:I10)/AVERAGE(E$12:I$12)*J$12 -> 2044575.7 | K10: =AVERAGE(F10:J10)/AVERAGE(F$12:J$12)*K$12 -> 2216688.4 | L10: =AVERAGE(G10:K10)/AVERAGE(G$12:K$12)*L$12 -> 2403981.5 | M10: =AVERAGE(H10:L10)/AVERAGE(H$12:L$12)*M$12 -> 2635701.3 | N10: =AVERAGE(I10:M10)/AVERAGE(I$12:M$12)*N$12 -> 2918663.4
B11: Export | C11: 2148 | D11: 2330 | E11: 102171 | F11: 96139 | G11: 238376 | H11: 395211 | I11: 283067 | J11: =AVERAGE(E11:I11)/AVERAGE(E$12:I$12)*J$12 -> 297586.22 | K11: =AVERAGE(F11:J11)/AVERAGE(F$12:J$12)*K$12 -> 352347.98 | L11: =AVERAGE(G11:K11)/AVERAGE(G$12:K$12)*L$12 -> 413905.57 | M11: =AVERAGE(H11:L11)/AVERAGE(H$12:L$12)*M$12 -> 455141.46 | N11: =AVERAGE(I11:M11)/AVERAGE(I$12:M$12)*N$12 -> 471575.05
B12: Total | C12: =SUM(C10:C11) -> 2253 | D12: =SUM(D10:D11) -> 2462 | E12: =SUM(E10:E11) -> 1563297 | F12: =SUM(F10:F11) -> 1457861 | G12: =SUM(G10:G11) -> 1652653 | H12: =SUM(H10:H11) -> 1966226 | I12: =SUM(I10:I11) -> 2135323 | J12: =I12*(1+J13) -> 2342161.9 | K12: =J12*(1+K13) -> 2569036.3 | L12: =K12*(1+L13) -> 2817887 | M12: =L12*(1+M13) -> 3090842.8 | N12: =M12*(1+N13) -> 3390238.5
B13: Growth in Employees Count | D13: =D12/C12-1 -> 0.092765202 | E13: =-16.1% -> -0.161 | F13: =F12/E12-1 -> -0.067444638 | G13: =G12/F12-1 -> 0.13361493 | H13: =H12/G12-1 -> 0.18973916 | J13: 0.096865392 | K13: 0.096865392 | L13: 0.096865392 | M13: 0.096865392 | N13: 0.096865392
B15: Domestic Sales of Segments | C15: =C2 -> FY18 | D15: =D2 -> FY19 | E15: =E2 -> FY20 | F15: =F2 -> FY21 | G15: =G2 -> FY22 | H15: =H2 -> FY23 | I15: =I2 -> FY24
B16: Mini (Sales) | C16: 0.684 | D16: 0.773 | E16: =E17*E4 -> 12026.157 | F16: =F17*F4 -> 10910.756 | G16: =G17*G4 -> 11394.57 | H16: =H17*H4 -> 11920.808 | I16: =I17*I4 -> 9470.2982 | J16: =I16+0.5% -> 9470.3032 | K16: =J16+0.5% -> 9470.3082 | L16: =K16+0.5% -> 9470.3132 | M16: =L16+0.5% -> 9470.3182 | N16: =M16+0.5% -> 9470.3232
A17: =A14*J12 -> 0 | B17: Mini(% of Domestic Sales) | E17: 0.17 | F17: 0.166 | G17: 0.15 | H17: 0.126 | I17: 0.077 | J17: 0.07 | K17: 0.07 | L17: 0.07 | M17: 0.07 | N17: 0.07
B18: Compact (Sales) | E18: =E19*E4 -> 38129.992 | F18: =F19*F4 -> 34704.093 | G18: =G19*G4 -> 37981.9 | H18: =H19*H4 -> 44088.069 | I18: =I19*I4 -> 54976.926 | J18: =J19*J4 -> 57800.661 | K18: =K19*K4 -> 57034.793 | L18: =L19*L4 -> 56979.227 | ... N18: =N19*N4 -> 59186.026
B19: Compact(% of Domestic Sales) | E19: 0.539 | F19: 0.528 | G19: 0.5 | H19: 0.466 | I19: 0.447 | J19: =AVERAGE(H19:I19) -> 0.4565 | K19: =AVERAGE(I19:J19) -> 0.45175 | L19: =AVERAGE($I$19:K19) -> 0.45175 | M19: =AVERAGE($I$19:L19) -> 0.45175 | N19: =AVERAGE($I$19:M19) -> 0.45175
B20: Mini + Compact (Sales) | E20: =E16+E18 -> 50156.149 | F20: =F16+F18 -> 45614.849 | G20: =G16+G18 -> 49376.47 | H20: =H16+H18 -> 56008.877 | I20: =I16+I18 -> 64447.224 | J20: =J16+J18 -> 67270.964 | K20: =K16+K18 -> 66505.101 | L20: =L16+L18 -> 66449.541 | ... N20: =N16+N18 -> 68656.349
B21: Mid Size (Sales) | E21: =E22*E4 -> 1202.6157 | F21: =F22*F4 -> 657.27448 | G21: =G22*G4 -> 759.638 | H21: =H22*H4 -> 747.41576 | I21: =I22*I4 -> 737.94532 | J21: =J22*J4 -> 879.98815 | K21: =K22*K4 -> 817.48817 | L21: =L22*L4 -> 846.64762 | ... N21: =N22*N4 -> 871.65917
B22: Mid Size(% of Domestic Sales) | E22: 0.017 | F22: 0.01 | G22: 0.01 | H22: 0.0079 | I22: 0.006 | J22: =AVERAGE(H22:I22) -> 0.00695 | K22: =AVERAGE(I22:J22) -> 0.006475 | L22: =AVERAGE(J22:K22) -> 0.0067125 | M22: =AVERAGE(K22:L22) -> 0.00659375 | N22: =AVERAGE(L22:M22) -> 0.006653125
B23: UV's (Sales) | E23: =E24*E4 -> 11389.478 | F23: =F24*F4 -> 11042.211 | G23: =G24*G4 -> 15952.398 | H23: =H24*H4 -> 18732.699 | I23: =I24*I4 -> 42677.837 | J23: =J24*J4 -> 43936.099 | K23: =K24*K4 -> 43809.791 | L23: =L24*L4 -> 43767.11 | ... N23: =N24*N4 -> 45462.205
B24: UV's (% of Domestic Sales) | E24: 0.161 | F24: 0.168 | G24: 0.21 | H24: 0.198 | I24: 0.347 | J24: 0.347 | K24: 0.347 | L24: 0.347 | M24: 0.347 | N24: 0.347
B25: Vans (Sales) | E25: =E26*E4 -> 5730.1101 | F25: =F26*F4 -> 5061.0135 | G25: =G26*G4 -> 6077.104 | H25: =H26*H4 -> 4825.0891 | I25: =I26*I4 -> 9101.3256 | J25: =J26*J4 -> 9192.3942 | K25: =K26*K4 -> 8953.8628 | L25: =L26*L4 -> 8791.7655 | ... N25: =N26*N4 -> 9298.6272
B26: Vans (% of Domestic Sales) | E26: 0.081 | F26: 0.077 | G26: 0.08 | H26: 0.051 | I26: 0.074 | J26: =AVERAGE(E26:I26) -> 0.0726 | K26: =AVERAGE(F26:J26) -> 0.07092 | L26: =AVERAGE(G26:K26) -> 0.069704 | M26: =AVERAGE(H26:L26) -> 0.0676448 | N26: =AVERAGE(I26:M26) -> 0.07097376
B27: LCV (Sales) | E27: =E28*E4 -> 1061.1315 | F27: =F28*F4 -> 1446.0039 | G27: =G28*G4 -> 1519.276 | H27: =H28*H4 -> 1892.1918 | I27: =I28*I4 -> 2213.8359 | J27: =J28*J4 -> 2405.723 | K27: =K28*K4 -> 2499.8094 | L27: =L28*L4 -> 2441.8768 | ... N27: =N28*N4 -> 2499.5566
B28: LCV (% of Domestic Sales) | E28: 0.015 | F28: 0.022 | G28: 0.02 | H28: 0.02 | I28: 0.018 | J28: =AVERAGE(E28:I28) -> 0.019 | K28: =AVERAGE(F28:J28) -> 0.0198 | L28: =AVERAGE(G28:K28) -> 0.01936 | M28: =AVERAGE(H28:L28) -> 0.019232 | N28: =AVERAGE(I28:M28) -> 0.0190784
B29: Other OEM Sales | E29: =E30*E4 -> 1202.6157 | F29: =F30*F4 -> 1840.3685 | G29: =G30*G4 -> 2278.914 | H29: =H30*H4 -> 3216.7261 | I29: =I30*I4 -> 3935.7084 | J29: =J30*J4 -> 3925.127 | K29: =K30*K4 -> 4008.5327 | L29: =L30*L4 -> 4059.8094 | ... N29: =N30*N4 -> 4148.9789
B30: OEM (% of Domestic Sales) | E30: 0.017 | F30: 0.028 | G30: 0.03 | H30: 0.034 | I30: 0.032 | J30: =AVERAGE(F30:I30) -> 0.031 | K30: =AVERAGE(G30:J30) -> 0.03175 | L30: =AVERAGE(H30:K30) -> 0.0321875 | M30: =AVERAGE(I30:L30) -> 0.031734375 | N30: =AVERAGE(J30:M30) -> 0.031667969

Sheet Assumptions
B2: Revenue Assumptions | C2: ='Profit & Loss Statement'!C3 -> FY18 | D2: ='Profit & Loss Statement'!D3 -> FY19 | E2: ='Profit & Loss Statement'!E3 -> FY20 | F2: ='Profit & Loss Statement'!F3 -> FY21 | G2: ='Profit & Loss Statement'!G3 -> FY22 | H2: ='Profit & Loss Statement'!H3 -> FY23 | I2: ='Profit & Loss Statement'!I3 -> FY24 | J2: ='Profit & Loss Statement'!J3 -> FY25E | ... N2: ='Profit & Loss Statement'!N3 -> FY29E
B3: Revenue from contracts with customers | C3: ='Profit & Loss Statement'!C5 -> 46761 | D3: ='Profit & Loss Statement'!D5 -> 59036 | E3: ='Profit & Loss Statement'!E5 -> 75660 | F3: ='Profit & Loss Statement'!F5 -> 70372 | G3: ='Profit & Loss Statement'!G5 -> 88330 | H3: ='Profit & Loss Statement'!H5 -> 118410 | I3: ='Profit & Loss Statement'!I5 -> 141858 | J3: ='Revenue Model'!J3 -> 145471.7 | K3: ='Revenue Model'!K3 -> 145107.7 | L3: ='Revenue Model'!L3 -> 144984.7 | M3: ='Revenue Model'!M3 -> 146605.35 | N3: ='Revenue Model'!N3 -> 149869.7
B4: Other Income | C4: ='Profit & Loss Statement'!C6 -> 1672 | D4: ='Profit & Loss Statement'!D6 -> 1145 | E4: ='Profit & Loss Statement'!E6 -> 3334 | F4: ='Profit & Loss Statement'!F6 -> 2936 | G4: ='Profit & Loss Statement'!G6 -> 1745 | H4: ='Profit & Loss Statement'!H6 -> 2265 | I4: ='Profit & Loss Statement'!I6 -> 4094 | J4: =J5*AVERAGE(I3:J3) -> 4743.1466 | K4: =K5*AVERAGE(J3:K3) -> 4317.6636 | L4: =L5*AVERAGE(K3:L3) -> 4006.0408 | M4: =M5*AVERAGE(L3:M3) -> 4190.8343 | N4: =N5*AVERAGE(M3:N3) -> 4463.6282
B5: As a % of Total Revenue | D5: =D4/C4-1 -> -0.31519139 | E5: =E4/AVERAGE(D3:E3) -> 0.049504068 | F5: =F4/AVERAGE(E3:F3) -> 0.040210365 | G5: =G4/AVERAGE(F3:G3) -> 0.021990901 | H5: =H4/AVERAGE(G3:H3) -> 0.02191158 | I5: =I4/AVERAGE(H3:I3) -> 0.03145988 | J5: =AVERAGE(E5:I5) -> 0.033015359 | K5: =AVERAGE(F5:J5) -> 0.029717617 | L5: =AVERAGE(G5:K5) -> 0.027619067 | M5: =AVERAGE(H5:L5) -> 0.028744701 | N5: =AVERAGE(I5:M5) -> 0.030111325
B6: Total | C6: =C3+C4 -> 48433 | D6: =D3+D4 -> 60181 | E6: =E3+E4 -> 78994 | F6: =F3+F4 -> 73308 | G6: =G3+G4 -> 90075 | H6: =H3+H4 -> 120675 | I6: =I3+I4 -> 145952 | J6: =J3+J4 -> 150214.85 | ... N6: =N3+N4 -> 154333.33
B8: Other P&L Assumptions: | E8: =E2 -> FY20 | F8: =F2 -> FY21 | G8: =G2 -> FY22 | H8: =H2 -> FY23 | I8: =I2 -> FY24
B9: Selling, General & Administrative Expenses | C9: ='Profit & Loss Statement'!C10 -> 35254 | D9: ='Profit & Loss Statement'!D10 -> 38505 | E9: ='Profit & Loss Statement'!E10 -> 8456 | F9: ='Profit & Loss Statement'!F10 -> 8208 | G9: ='Profit & Loss Statement'!G10 -> 9437 | H9: ='Profit & Loss Statement'!H10 -> 10316 | I9: ='Profit & Loss Statement'!I10 -> 12083 | J9: =J10*J11 -> 13403.71 | K9: =K10*K11 -> 14868.779 | L9: =L10*L11 -> 16493.984 | M9: =M10*M11 -> 18296.829 | N9: =N10*N11 -> 20296.731
B10: Employee Count | C10: ='Revenue Model'!C12 -> 2253 | D10: ='Revenue Model'!D12 -> 2462 | E10: ='Revenue Model'!E12 -> 1563297 | F10: ='Revenue Model'!F12 -> 1457861 | G10: ='Revenue Model'!G12 -> 1652653 | H10: ='Revenue Model'!H12 -> 1966226 | I10: ='Revenue Model'!I12 -> 2135323 | J10: ='Revenue Model'!J12 -> 2342161.9 | ... N10: ='Revenue Model'!N12 -> 3390238.5
B11: Cost per employee | C11: =C9/C10 -> 15.647581 | D11: =D9/D10 -> 15.639724 | E11: =E9/E10 -> 0.0054090809 | F11: =F9/F10 -> 0.0056301664 | G11: =G9/G10 -> 0.0057102126 | H11: =H9/H10 -> 0.0052465993 | I11: =I9/I10 -> 0.0056586287 | J11: =I11*(1+J12) -> 0.0057227942 | K11: =J11*(1+K12) -> 0.0057876873 | L11: =K11*(1+L12) -> 0.0058533162 | M11: =L11*(1+M12) -> 0.0059196893 | N11: =M11*(1+N12) -> 0.0059868151
B12: Growth Rate of expense per employee | G12: 0.01x(1+CAGR)^4 = 0.01 | I12: =(I11/E11)^(1/4)-1 -> 0.011339406 | J12: =(I11/E11)^(1/4)-1 -> 0.011339406 | K12: =(I11/E11)^(1/4)-1 -> 0.011339406 | L12: =(I11/E11)^(1/4)-1 -> 0.011339406 | M12: =(I11/E11)^(1/4)-1 -> 0.011339406 | N12: =(I11/E11)^(1/4)-1 -> 0.011339406
B13: Total Operating Expenses | C13: ='Profit & Loss Statement'!C13 -> 13862 | D13: ='Profit & Loss Statement'!D13 -> 15048 | E13: ='Profit & Loss Statement'!E13 -> 63420 | F13: ='Profit & Loss Statement'!F13 -> 59846 | G13: ='Profit & Loss Statement'!G13 -> 75976 | H13: ='Profit & Loss Statement'!H13 -> 99846 | I13: ='Profit & Loss Statement'!I13 -> 116505 | J13: =J14*AVERAGE(I3:J3) -> 131595.58 | K13: =K14*AVERAGE(J3:K3) -> 132337.54 | L13: =L14*AVERAGE(K3:L3) -> 134762.1 | M13: =M14*AVERAGE(L3:M3) -> 134630.6 | N13: =N14*AVERAGE(M3:N3) -> 135626.49
B14: As a percent of revenue | C14: =C13/C3 -> 0.29644362 | D14: =D13/D3 -> 0.25489532 | E14: =E13/AVERAGE(D3:E3) -> 0.94167607 | F14: =F13/AVERAGE(E3:F3) -> 0.81962857 | G14: =G13/AVERAGE(F3:G3) -> 0.95746745 | H14: =H13/AVERAGE(G3:H3) -> 0.96590887 | I14: =I13/AVERAGE(H3:I3) -> 0.89526949 | J14: =AVERAGE(E14:I14) -> 0.91599009 | K14: =AVERAGE(F14:J14) -> 0.9108529 | L14: =AVERAGE(G14:K14) -> 0.92909776 | M14: =AVERAGE(H14:L14) -> 0.92342382 | N14: =AVERAGE(I14:M14) -> 0.91492681
B15: Exceptional items- Impairment of goodwill | C15: ='Profit & Loss Statement'!C17 -> 0 | D15: ='Profit & Loss Statement'!D17 -> 1258 | E15: ='Profit & Loss Statement'!E17 -> 134 | F15: ='Profit & Loss Statement'!F17 -> 102 | G15: ='Profit & Loss Statement'!G17 -> 127 | H15: ='Profit & Loss Statement'!H17 -> 252 | I15: ='Profit & Loss Statement'!I17 -> 194 | J15: 0 | K15: 0 | L15: 0 | M15: 0 | N15: 0
B16: Profit before tax | E16: ='Profit & Loss Statement'!E18 -> 7103 | F16: ='Profit & Loss Statement'!F18 -> 5321 | G16: ='Profit & Loss Statement'!G18 -> 4697 | H16: ='Profit & Loss Statement'!H18 -> 10439 | I16: ='Profit & Loss Statement'!I18 -> 17424 | J16: ='Profit & Loss Statement'!J18 -> 26218.578 | K16: ='Profit & Loss Statement'!K18 -> 37846.999 | L16: ='Profit & Loss Statement'!L18 -> 51522.612 | ... N16: ='Profit & Loss Statement'!N18 -> 84533.923
B17: Tax Rate | J17: 0.2517 | K17: 0.2517 | L17: 0.2517 | M17: 0.2517 | N17: 0.2517 | P17: Corporate tax rate in india
B18: Tax expense | J18: =J16*J17 -> 6599.216 | K18: =K16*K17 -> 9526.0896 | L18: =L16*L17 -> 12968.241 | M18: =M16*M17 -> 16873.505 | N18: =N16*N17 -> 21277.188 | P18: 0.2517
B21: Other Balance Sheet Assumptions | C21: =C2 -> FY18 | D21: =D2 -> FY19 | E21: =E2 -> FY20 | F21: =F2 -> FY21 | G21: =G2 -> FY22 | H21: =H2 -> FY23 | I21: =I2 -> FY24 | J21: =J2 -> FY25E | ... N21: =N2 -> FY29E
B22: Capital work in progress | C22: ='Balance Sheet'!C6 -> 14 | D22: ='Balance Sheet'!D6 -> 0 | E22: ='Balance Sheet'!E6 -> 1344 | F22: ='Balance Sheet'!F6 -> 1199 | G22: ='Balance Sheet'!G6 -> 2646 | H22: ='Balance Sheet'!H6 -> 4054 | I22: ='Balance Sheet'!I6 -> 7504 | J22: =I22*40%+H22*30%+G22*10%+F22*10%+E22*10% -> 4736.7 | K22: =J22*40%+I22*30%+H22*10%+G22*10%+F22*10% -> 4935.78 | L22: =K22*40%+J22*30%+I22*10%+H22*10%+G22*10% -> 4815.722 | M22: =L22*40%+K22*30%+J22*10%+I22*10%+H22*10% -> 5036.4928 | N22: =M22*40%+L22*30%+K22*10%+J22*10%+I22*10% -> 5176.9617
B23: Goodwill | C23: ='Balance Sheet'!C7 -> 2961 | D23: ='Balance Sheet'!D7 -> 1736 | E23: ='Balance Sheet'!E7 -> 0 | F23: ='Balance Sheet'!F7 -> 0 | G23: ='Balance Sheet'!G7 -> 0 | H23: ='Balance Sheet'!H7 -> 0 | I23: ='Balance Sheet'!I7 -> 0 | J23: =I23 -> 0 | K23: =J23 -> 0 | L23: =K23 -> 0 | M23: =L23 -> 0 | N23: =M23 -> 0
B24: Intangible assets under development | C24: ='Balance Sheet'!C9 -> 0 | D24: ='Balance Sheet'!D9 -> 17 | E24: ='Balance Sheet'!E9 -> 71 | F24: ='Balance Sheet'!F9 -> 298 | G24: ='Balance Sheet'!G9 -> 290 | H24: ='Balance Sheet'!H9 -> 89 | I24: ='Balance Sheet'!I9 -> 230 | J24: =I24*40%+H24*30%+G24*10%+F24*10%+E24*10% -> 184.6 | K24: =J24*40%+I24*30%+H24*10%+G24*10%+F24*10% -> 210.54 | L24: =K24*40%+J24*30%+I24*10%+H24*10%+G24*10% -> 200.496 | M24: =L24*40%+K24*30%+J24*10%+I24*10%+H24*10% -> 193.7204 | N24: =M24*40%+L24*30%+K24*10%+J24*10%+I24*10% -> 200.15096
B26: Financial Assets
B27: i. Loans | C27: ='Balance Sheet'!C13 -> 585 | D27: ='Balance Sheet'!D13 -> 618 | E27: ='Balance Sheet'!E13 -> 0.2 | F27: ='Balance Sheet'!F13 -> 0.2 | G27: ='Balance Sheet'!G13 -> 0.2 | H27: ='Balance Sheet'!H13 -> 0.2 | I27: ='Balance Sheet'!I13 -> 0.1 | J27: =I27*40%+H27*30%+G27*10%+F27*10%+E27*10% -> 0.16 | K27: =J27*40%+I27*30%+H27*10%+G27*10%+F27*10% -> 0.154 | L27: =K27*40%+J27*30%+I27*10%+H27*10%+G27*10% -> 0.1596 | M27: =L27*40%+K27*30%+J27*10%+I27*10%+H27*10% -> 0.15604 | N27: =M27*40%+L27*30%+K27*10%+J27*10%+I27*10% -> 0.151696
B28: ii. Other Financial assets | C28: ='Balance Sheet'!C14 -> 185 | D28: ='Balance Sheet'!D14 -> 239 | E28: ='Balance Sheet'!E14 -> 36.5 | F28: ='Balance Sheet'!F14 -> 37 | G28: ='Balance Sheet'!G14 -> 37.5 | H28: ='Balance Sheet'!H14 -> 240 | I28: ='Balance Sheet'!I14 -> 298 | J28: =I28*40%+H28*30%+G28*10%+F28*10%+E28*10% -> 202.3 | K28: =J28*40%+I28*30%+H28*10%+G28*10%+F28*10% -> 201.77 | L28: =K28*40%+J28*30%+I28*10%+H28*10%+G28*10% -> 198.948 | M28: =L28*40%+K28*30%+J28*10%+I28*10%+H28*10% -> 214.1402 | N28: =M28*40%+L28*30%+K28*10%+J28*10%+I28*10% -> 215.54748
B29: Income tax assets (net) | C29: ='Balance Sheet'!C15 -> 584 | D29: ='Balance Sheet'!D15 -> 920 | E29: ='Balance Sheet'!E15 -> 0 | F29: ='Balance Sheet'!F15 -> 541 | G29: ='Balance Sheet'!G15 -> 545 | H29: ='Balance Sheet'!H15 -> 605 | I29: ='Balance Sheet'!I15 -> 584 | J29: =I29*40%+H29*30%+G29*10%+F29*10%+E29*10% -> 523.7 | K29: =J29*40%+I29*30%+H29*10%+G29*10%+F29*10% -> 553.78 | L29: =K29*40%+J29*30%+I29*10%+H29*10%+G29*10% -> 552.022 | M29: =L29*40%+K29*30%+J29*10%+I29*10%+H29*10% -> 558.2128 | N29: =M29*40%+L29*30%+K29*10%+J29*10%+I29*10% -> 555.03972
B30: Other Assets | C30: ='Balance Sheet'!C16 -> 40 | D30: ='Balance Sheet'!D16 -> 48 | E30: ='Balance Sheet'!E16 -> 1722 | F30: ='Balance Sheet'!F16 -> 1687 | G30: ='Balance Sheet'!G16 -> 2520 | H30: ='Balance Sheet'!H16 -> 2323 | I30: ='Balance Sheet'!I16 -> 2805 | J30: =I30*40%+H30*30%+G30*10%+F30*10%+E30*10% -> 2411.8 | K30: =J30*40%+I30*30%+H30*10%+G30*10%+F30*10% -> 2459.22 | L30: =K30*40%+J30*30%+I30*10%+H30*10%+G30*10% -> 2472.028 | M30: =L30*40%+K30*30%+J30*10%+I30*10%+H30*10% -> 2480.5572 | N30: =M30*40%+L30*30%+K30*10%+J30*10%+I30*10% -> 2501.4333
B31: Deferred tax assets (net) | C31: ='Balance Sheet'!C17 -> 0 | D31: ='Balance Sheet'!D17 -> 0 | E31: ='Balance Sheet'!E17 -> 0 | F31: ='Balance Sheet'!F17 -> 0 | G31: ='Balance Sheet'!G17 -> 141 | H31: ='Balance Sheet'!H17 -> 279 | I31: ='Balance Sheet'!I17 -> 47 | J31: =I31*40%+H31*30%+G31*10%+F31*10%+E31*10% -> 116.6 | K31: =J31*40%+I31*30%+H31*10%+G31*10%+F31*10% -> 102.74 | L31: =K31*40%+J31*30%+I31*10%+H31*10%+G31*10% -> 122.776 | M31: =L31*40%+K31*30%+J31*10%+I31*10%+H31*10% -> 124.1924 | N31: =M31*40%+L31*30%+K31*10%+J31*10%+I31*10% -> 113.14376
B33: Equity
B34: Equity share capital | C34: ='Balance Sheet'!C34 -> 375 | D34: ='Balance Sheet'!D34 -> 597 | E34: ='Balance Sheet'!E34 -> 151 | F34: ='Balance Sheet'!F34 -> 151 | G34: ='Balance Sheet'!G34 -> 151 | H34: ='Balance Sheet'!H34 -> 157 | I34: ='Balance Sheet'!I34 -> 157 | J34: =I34 -> 157 | K34: =J34 -> 157 | L34: =K34 -> 157 | M34: =L34 -> 157 | N34: =M34 -> 157
B35: Instruments entirely in the nature of equity | C35: ='Balance Sheet'!C35 -> 2229 | D35: ='Balance Sheet'!D35 -> 2230 | E35: ='Balance Sheet'!E35 -> 19 | F35: ='Balance Sheet'!F35 -> 0 | G35: ='Balance Sheet'!G35 -> 0 | H35: ='Balance Sheet'!H35 -> 0 | I35: ='Balance Sheet'!I35 -> 0 | J35: 0 | K35: 0 | L35: 0 | M35: 0 | N35: 0
B36: Other equity (Reserves & Surplus) | C36: ='Balance Sheet'!C36 -> -13492 | D36: ='Balance Sheet'!D36 -> -9432 | E36: ='Balance Sheet'!E36 -> 49262 | F36: ='Balance Sheet'!F36 -> 52350 | G36: ='Balance Sheet'!G36 -> 55182 | H36: ='Balance Sheet'!H36 -> 74443 | I36: ='Balance Sheet'!I36 -> 85479 | J36: =I36+'Profit & Loss Statement'!J25 -> 105098.36 | K36: =J36+'Profit & Loss Statement'!K25 -> 133419.27 | L36: =K36+'Profit & Loss Statement'!L25 -> 171973.64 | M36: =L36+'Profit & Loss Statement'!M25 -> 222138.3 | N36: =M36+'Profit & Loss Statement'!N25 -> 285395.03
B38: Other Financial Liabilities | C38: ='Balance Sheet'!C43 -> 0 | D38: ='Balance Sheet'!D43 -> 0 | E38: ='Balance Sheet'!E43 -> 2116 | F38: ='Balance Sheet'!F43 -> 2129 | G38: ='Balance Sheet'!G43 -> 2181 | H38: ='Balance Sheet'!H43 -> 2585 | I38: ='Balance Sheet'!I43 -> 3162 | J38: =I38*40%+H38*30%+G38*10%+F38*10%+E38*10% -> 2682.9 | K38: =J38*40%+I38*30%+H38*10%+G38*10%+F38*10% -> 2711.26 | L38: =K38*40%+J38*30%+I38*10%+H38*10%+G38*10% -> 2682.174 | M38: =L38*40%+K38*30%+J38*10%+I38*10%+H38*10% -> 2729.2376 | N38: =M38*40%+L38*30%+K38*10%+J38*10%+I38*10% -> 2751.9632
B39: Provisions | C39: ='Balance Sheet'!C44 -> 812 | D39: ='Balance Sheet'!D44 -> 940 | E39: ='Balance Sheet'!E44 -> 52 | F39: ='Balance Sheet'!F44 -> 45 | G39: ='Balance Sheet'!G44 -> 84 | H39: ='Balance Sheet'!H44 -> 87 | I39: ='Balance Sheet'!I44 -> 145 | J39: =I39*40%+H39*30%+G39*10%+F39*10%+E39*10% -> 102.2 | K39: =J39*40%+I39*30%+H39*10%+G39*10%+F39*10% -> 105.98 | L39: =K39*40%+J39*30%+I39*10%+H39*10%+G39*10% -> 104.652 | M39: =L39*40%+K39*30%+J39*10%+I39*10%+H39*10% -> 107.0748 | N39: =M39*40%+L39*30%+K39*10%+J39*10%+I39*10% -> 109.54352
B40: Deferred tax liabilities (net) | C40: ='Balance Sheet'!C45 -> 123 | D40: ='Balance Sheet'!D45 -> 0 | E40: ='Balance Sheet'!E45 -> 658 | F40: ='Balance Sheet'!F45 -> 445 | G40: ='Balance Sheet'!G45 -> 0 | H40: ='Balance Sheet'!H45 -> 321 | I40: ='Balance Sheet'!I45 -> 389 | J40: =I40*40%+H40*30%+G40*10%+F40*10%+E40*10% -> 362.2 | K40: =J40*40%+I40*30%+H40*10%+G40*10%+F40*10% -> 338.18 | L40: =K40*40%+J40*30%+I40*10%+H40*10%+G40*10% -> 314.932 | M40: =L40*40%+K40*30%+J40*10%+I40*10%+H40*10% -> 334.6468 | N40: =M40*40%+L40*30%+K40*10%+J40*10%+I40*10% -> 337.27632

Sheet WACC
B1: Maruti Suzuki | C1: Nifty 50 | E1: Returns/Maruti | F1: Returns/Nifty 50 | N1: Nifty 100
A2: 45687 | B2: 12000 | C2: =N2*2 -> 23292.301 | K2: CMP (Current Market Price) | L2: 12310.65 | N2: 11646.15
A3: 45686 | B3: 11977.9 | C3: =N3*2 -> 23280.4 | E3: =B3/B2-1 -> -0.0018416667 | F3: =C3/C2-1 -> -0.00051091526 | K3: No. of Shares in Cr | L3: 31.44 | N3: 11640.2
A4: 45685 | B4: 12123.75 | C4: =N4*2 -> 22734.5 | E4: =B4/B3-1 -> 0.012176592 | F4: =C4/C3-1 -> -0.023448926 | N4: 11367.25
A5: 45684 | B5: 11993.85 | C5: =N5*2 -> 22529.1 | E5: =B5/B4-1 -> -0.010714507 | F5: =C5/C4-1 -> -0.0090347441 | I5: =SLOPE(E3:E926,F3:F926) -> 0.00060484148 | N5: 11264.55
A6: 45681 | B6: 11967.9 | C6: =N6*2 -> 22483.199 | E6: =B6/B5-1 -> -0.0021636088 | F6: =C6/C5-1 -> -0.0020373824 | N6: 11241.6
A7: 45680 | B7: 12045.75 | C7: =N7*2 -> 21844.5 | E7: =B7/B6-1 -> 0.0065049006 | F7: =C7/C6-1 -> -0.028407844 | H7: WACC | N7: 10922.25
A8: 45679 | B8: 12020.35 | C8: =N8*2 -> 22352.6 | E8: =B8/B7-1 -> -0.0021086275 | F8: =C8/C7-1 -> 0.023259842 | H8: Beta | I8: =_xlfn.COVARIANCE.S(E3:E251,F3:F251)/_xlfn.VAR.S(F3:F251) -> 0.00060484148 | N8: 11176.3
A9: 45678 | B9: 11883.7 | C9: =N9*2 -> 22730.5 | E9: =B9/B8-1 -> -0.011368221 | F9: =C9/C8-1 -> 0.016906328 | H9: Risk Free Rate | I9: 0.0691 | N9: 11365.25
A10: 45677 | B10: 12020.05 | C10: =N10*2 -> 22707.301 | E10: =B10/B9-1 -> 0.011473699 | F10: =C10/C9-1 -> -0.0010206207 | H10: Equity Risk Premium | I10: 0.0781 | K10: Terminal Growth Rate Calculation | N10: 11353.65
A11: 45674 | B11: 12136.35 | C11: =N11*2 -> 22770.4 | E11: =B11/B10-1 -> 0.0096755005 | F11: =C11/C10-1 -> 0.0027788247 | K11: GDP USA | L11: 0.037 | M11: 0.4 | N11: 11385.2
A12: 45673 | B12: 12092.3 | C12: =N12*2 -> 23091.801 | E12: =B12/B11-1 -> -0.0036295921 | F12: =C12/C11-1 -> 0.014114833 | H12: Cost Of Equity | I12: =I9+(I8*I10) -> 0.069147238 | K12: US Automobile Sector Growth | L12: 0.035 | M12: 0.3 | N12: 11545.9
A13: 45672 | B13: 11947.4 | C13: =N13*2 -> 23251.199 | E13: =B13/B12-1 -> -0.011982832 | F13: =C13/C12-1 -> 0.0069028153 | K13: GDP India | L13: 0.068 | M13: 0.2 | N13: 11625.6
A14: 45671 | B14: 11741.15 | C14: =N14*2 -> 23541.5 | E14: =B14/B13-1 -> -0.01726317 | F14: =C14/C13-1 -> 0.012485411 | H14: Market Value of Equity | I14: =L2*L3 -> 387046.84 | K14: Worldwide Automobile Industry Growth | L14: 0.0677 | M14: 0.1 | N14: 11770.75
A15: 45670 | B15: 11497.7 | C15: =N15*2 -> 23667.801 | E15: =B15/B14-1 -> -0.020734766 | F15: =C15/C14-1 -> 0.005365027 | H15: Value Of Debt | I15: =Schedules_Populated!J44+Schedules_Populated!J48 -> 123.9 | K15: Terminal Growth Rate | M15: 0.0538 | N15: 11833.9
A16: 45667 | B16: 11631.1 | C16: =N16*2 -> 23850.801 | E16: =B16/B15-1 -> 0.01160232 | F16: =C16/C15-1 -> 0.0077320238 | H16: Cost of Debt | I16: =Schedules_Populated!J53/(Schedules_Populated!J44+Schedules_Populated!J48) -> 1.6821802 | N16: 11925.4
A17: 45666 | B17: 11740.55 | C17: =N17*2 -> 23981.4 | E17: =B17/B16-1 -> 0.009410116 | F17: =C17/C16-1 -> 0.0054756907 | H17: =H12 -> Cost Of Equity | I17: =I12 -> 0.069147238 | N17: 11990.7
A18: 45665 | B18: 11822 | C18: =N18*2 -> 23998.1 | E18: =B18/B17-1 -> 0.0069374944 | F18: =C18/C17-1 -> 0.00069634049 | H18: Proportion of Debt | I18: =I15/(I14+I15) -> 0.00032001386 | N18: 11999.05
A19: 45664 | B19: 11721.3 | C19: =N19*2 -> 23991.4 | E19: =B19/B18-1 -> -0.0085180173 | F19: =C19/C18-1 -> -0.00027915627 | H19: Proportion of Equity | I19: =1-I18 -> 0.99967999 | K19: Terminal growth rate cannot exceed long term growth rate of country (Should be 4 - 6.5%) | N19: 11995.7
A20: 45663 | B20: 11755.65 | C20: =N20*2 -> 24078.1 | E20: =B20/B19-1 -> 0.0029305623 | F20: =C20/C19-1 -> 0.0036137624 | H20: Effective Tax rate | I20: 0.2517 | L20: 0.065 | N20: 12039.05
A21: 45660 | B21: 11934.25 | C21: =N21*2 -> 23516.4 | E21: =B21/B20-1 -> 0.015192695 | F21: =C21/C20-1 -> -0.023328221 | H21: WACC | I21: =(I16*I18*(1-I20))+(I17*I19) -> 0.069527936 | L21: 0.07 | N21: 11758.2
A22: 45659 | B22: 11841.3 | C22: =N22*2 -> 23686.699 | E22: =B22/B21-1 -> -0.0077885079 | F22: =C22/C21-1 -> 0.0072417047 | N22: 11843.35
A23: 45658 | B23: 11208.3 | C23: =N23*2 -> 23905.801 | E23: =B23/B22-1 -> -0.053456968 | F23: =C23/C22-1 -> 0.009249983 | N23: 11952.9
A24: 45657 | B24: 10858.4 | C24: =N24*2 -> 23953.699 | E24: =B24/B23-1 -> -0.031217937 | F24: =C24/C23-1 -> 0.0020036324 | N24: 11976.85
A25: 45656 | B25: 10798.95 | C25: =N25*2 -> 24018 | E25: =B25/B24-1 -> -0.0054750239 | F25: =C25/C24-1 -> 0.0026843779 | N25: 12009
A26: 45653 | B26: 10941.05 | C26: =N26*2 -> 23943.6 | E26: =B26/B25-1 -> 0.013158687 | F26: =C26/C25-1 -> -0.003097693 | N26: 11971.8
A27: 45652 | B27: 10896 | C27: =N27*2 -> 24012.199 | E27: =B27/B26-1 -> -0.0041175207 | F27: =C27/C26-1 -> 0.0028650499 | N27: 12006.1
A28: 45650 | B28: 10736.6 | C28: =N28*2 -> 23685.4 | E28: =B28/B27-1 -> -0.014629222 | F28: =C28/C27-1 -> -0.0136097 | N28: 11842.7
A29: 45649 | B29: 10822 | C29: =N29*2 -> 23943.801 | E29: =B29/B28-1 -> 0.0079541009 | F29: =C29/C28-1 -> 0.010909691 | N29: 11971.9
A30: 45646 | B30: 10901.05 | C30: =N30*2 -> 23638.1 | E30: =B30/B29-1 -> 0.0073045648 | F30: =C30/C29-1 -> -0.012767446 | N30: 11819.05
A31: 45645 | B31: 10955.35 | C31: =N31*2 -> 23548.801 | E31: =B31/B30-1 -> 0.0049811715 | F31: =C31/C30-1 -> -0.0037777499 | N31: 11774.4
A32: 45644 | B32: 11002.45 | C32: =N32*2 -> 23497.9 | E32: =B32/B31-1 -> 0.0042992693 | F32: =C32/C31-1 -> -0.0021614855 | N32: 11748.95
A33: 45643 | B33: 11108.55 | C33: =N33*2 -> 23555.699 | E33: =B33/B32-1 -> 0.0096433067 | F33: =C33/C32-1 -> 0.0024597444 | N33: 11777.85
A34: 45642 | B34: 11277 | C34: =N34*2 -> 23826.699 | E34: =B34/B33-1 -> 0.015163995 | F34: =C34/C33-1 -> 0.011504647 | N34: 11913.35
A35: 45639 | B35: 11272.55 | C35: =N2*2 -> 23292.301 | E35: =B35/B34-1 -> -0.0003946085 | F35: =C35/C34-1 -> -0.022428555 | N35: 12007.1
A36: 45638 | B36: 11167.4 | C36: =N3*2 -> 23280.4 | E36: =B36/B35-1 -> -0.0093279693 | F36: =C36/C35-1 -> -0.00051091526 | N36: 12217.9
A37: 45637 | B37: 11277.75 | C37: =N4*2 -> 22734.5 | E37: =B37/B36-1 -> 0.0098814406 | F37: =C37/C36-1 -> -0.023448926 | N37: 12349.15
A38: 45636 | B38: 11198.2 | C38: =N5*2 -> 22529.1 | E38: =B38/B37-1 -> -0.007053712 | F38: =C38/C37-1 -> -0.0090347441 | N38: 12545.45
A39: 45635 | B39: 11279.8 | C39: =N6*2 -> 22483.199 | E39: =B39/B38-1 -> 0.0072868854 | F39: =C39/C38-1 -> -0.0020373824 | N39: 12683.35
A40: 45632 | B40: 11317.95 | C40: =N7*2 -> 21844.5 | E40: =B40/B39-1 -> 0.0033821522 | F40: =C40/C39-1 -> -0.028407844 | N40: 12805.6
A41: 45631 | B41: 11182.25 | C41: =N8*2 -> 22352.6 | E41: =B41/B40-1 -> -0.011989804 | F41: =C41/C40-1 -> 0.023259842 | N41: 12764.05
A42: 45630 | B42: 11129.85 | C42: =N9*2 -> 22730.5 | E42: =B42/B41-1 -> -0.0046859979 | F42: =C42/C41-1 -> 0.016906328 | N42: 12804.25
A43: 45629 | B43: 11279.25 | C43: =N10*2 -> 22707.301 | E43: =B43/B42-1 -> 0.013423362 | F43: =C43/C42-1 -> -0.0010206207 | N43: 12804.25
A44: 45628 | B44: 11239.3 | C44: =N11*2 -> 22770.4 | E44: =B44/B43-1 -> -0.0035419022 | F44: =C44/C43-1 -> 0.0027788247 | N44: 12960.9
A45: 45625 | B45: 11074.2 | C45: =N12*2 -> 23091.801 | E45: =B45/B44-1 -> -0.014689527 | F45: =C45/C44-1 -> 0.014114833 | N45: 13022.75
A46: 45624 | B46: 10949.85 | C46: =N13*2 -> 23251.199 | E46: =B46/B45-1 -> -0.011228802 | F46: =C46/C45-1 -> 0.0069028153 | N46: 12864.85
A47: 45623 | B47: 11058.35 | C47: =N14*2 -> 23541.5 | E47: =B47/B46-1 -> 0.0099088115 | F47: =C47/C46-1 -> 0.012485411 | N47: 12962.45
A48: 45622 | B48: 10943.95 | C48: =N2*2 -> 23292.301 | E48: =B48/B47-1 -> -0.010345124 | F48: =C48/C47-1 -> -0.010585528 | N48: 13036.65
A49: 45621 | B49: 11025.15 | C49: =N3*2 -> 23280.4 | E49: =B49/B48-1 -> 0.0074196245 | F49: =C49/C48-1 -> -0.00051091526 | N49: 13158.3
A50: 45618 | B50: 11063.6 | C50: =N4*2 -> 22734.5 | E50: =B50/B49-1 -> 0.0034874809 | F50: =C50/C49-1 -> -0.023448926 | N50: 12959.8
A51: 45617 | B51: 10861.45 | C51: =N5*2 -> 22529.1 | E51: =B51/B50-1 -> -0.018271629 | F51: =C51/C50-1 -> -0.0090347441 | N51: 13087.75
A52: 45615 | B52: 10959.3 | C52: =N6*2 -> 22483.199 | E52: =B52/B51-1 -> 0.0090089261 | F52: =C52/C51-1 -> -0.0020373824 | N52: 13080.3
A53: 45614 | B53: 11093.95 | C53: =N7*2 -> 21844.5 | E53: =B53/B52-1 -> 0.012286369 | F53: =C53/C52-1 -> -0.028407844 | N53: 13225.7
A54: 45610 | B54: 11006.05 | C54: =N8*2 -> 22352.6 | E54: =B54/B53-1 -> -0.0079232374 | F54: =C54/C53-1 -> 0.023259842 | N54: 13244.35
A55: 45609 | B55: 11049.6 | C55: =N9*2 -> 22730.5 | E55: =B55/B54-1 -> 0.0039569146 | F55: =C55/C54-1 -> 0.016906328 | N55: 13280.5
A56: 45608 | B56: 11143.1 | C56: =N10*2 -> 22707.301 | E56: =B56/B55-1 -> 0.0084618448 | F56: =C56/C55-1 -> -0.0010206207 | N56: 13396.5
A57: 45607 | B57: 11399.7 | C57: =N11*2 -> 22770.4 | E57: =B57/B56-1 -> 0.023027703 | F57: =C57/C56-1 -> 0.0027788247 | N57: 13497.85
A58: 45604 | B58: 11303 | C58: =N12*2 -> 23091.801 | E58: =B58/B57-1 -> -0.0084826794 | F58: =C58/C57-1 -> 0.014114833 | N58: 13529.85
A59: 45603 | B59: 11300.15 | C59: =N13*2 -> 23251.199 | E59: =B59/B58-1 -> -0.00025214545 | F59: =C59/C58-1 -> 0.0069028153 | N59: 13649.6
... A80: 45574 | B80: 12760.7 | C80: =N34*2 -> 23826.699 | E80: =B80/B79-1 -> -0.014168617 | F80: =C80/C79-1 -> 0.011504647 | N80: 14514.35
A81: 45573 | B81: 12531.95 | C81: =N10*2 -> 22707.301 | E81: =B81/B80-1 -> -0.017926133 | F81: =C81/C80-1 -> -0.046980844 | N81: 14642.05
A82: 45572 | B82: 12527.5 | C82: =N11*2 -> 22770.4 | E82: =B82/B81-1 -> -0.00035509238 | F82: =C82/C81-1 -> 0.0027788247 | N82: 14705.5
A83: 45569 | B83: 12605.75 | C83: =N12*2 -> 23091.801 | E83: =B83/B82-1 -> 0.0062462582 | F83: =C83/C82-1 -> 0.014114833 | N83: 14694.95
A84: 45568 | B84: 12647.35 | C84: =N13*2 -> 23251.199 | E84: =B84/B83-1 -> 0.0033000813 | F84: =C84/C83-1 -> 0.0069028153 | N84: 14731.15
A85: 45566 | B85: 13166 | C85: =N14*2 -> 23541.5 | E85: =B85/B84-1 -> 0.041008591 | F85: =C85/C84-1 -> 0.012485411 | N85: 14558.8
A86: 45565 | B86: 13238 | C86: =N15*2 -> 23667.801 | E86: =B86/B85-1 -> 0.0054686313 | F86: =C86/C85-1 -> 0.005365027 | N86: 14390.05
A87: 45562 | B87: 13495.6 | C87: =N16*2 -> 23850.801 | E87: =B87/B86-1 -> 0.019459133 | F87: =C87/C86-1 -> 0.0077320238 | N87: 14632.2
A88: 45561 | B88: 13383.8 | C88: =N17*2 -> 23981.4 | E88: =B88/B87-1 -> -0.0082841815 | F88: =C88/C87-1 -> 0.0054756907 | N88: 14751.3
A89: 45560 | B89: 12785.3 | C89: =N18*2 -> 23998.1 | E89: =B89/B88-1 -> -0.044718241 | F89: =C89/C88-1 -> 0.00069634049 | N89: 14686.55
A90: 45559 | B90: 12738.6 | C90: =N19*2 -> 23991.4 | E90: =B90/B89-1 -> -0.0036526323 | F90: =C90/C89-1 -> -0.00027915627 | N90: 14479.6
A91: 45558 | B91: 12683.1 | C91: =N20*2 -> 24078.1 | E91: =B91/B90-1 -> -0.0043568367 | F91: =C91/C90-1 -> 0.0036137624 | N91: 14348.45
A92: 45555 | B92: 12614.5 | C92: =N21*2 -> 23516.4 | E92: =B92/B91-1 -> -0.0054087723 | F92: =C92/C91-1 -> -0.023328221 | N92: 14085.85
A93: 45554 | B93: 12351.5 | C93: =N22*2 -> 23686.699 | E93: =B93/B92-1 -> -0.020849023 | F93: =C93/C92-1 -> 0.0072417047 | N93: 13947.25
A94: 45553 | B94: 12204.1 | C94: =N10*2 -> 22707.301 | E94: =B94/B93-1 -> -0.011933773 | F94: =C94/C93-1 -> -0.041348034 | N94: 13743.3
A95: 45552 | B95: 12245.75 | C95: =N11*2 -> 22770.4 | E95: =B95/B94-1 -> 0.0034127875 | F95: =C95/C94-1 -> 0.0027788247 | N95: 14361.65
A96: 45551 | B96: 12289 | C96: =N12*2 -> 23091.801 | E96: =B96/B95-1 -> 0.0035318376 | F96: =C96/C95-1 -> 0.014114833 | N96: 14720.55
A97: 45548 | B97: 12316.05 | C97: =N13*2 -> 23251.199 | E97: =B97/B96-1 -> 0.0022011555 | F97: =C97/C96-1 -> 0.0069028153 | N97: 14854
A98: 45547 | B98: 12400.85 | C98: =N14*2 -> 23541.5 | E98: =B98/B97-1 -> 0.0068853244 | F98: =C98/C97-1 -> 0.012485411 | N98: 14977.15
A99: 45546 | B99: 12242.6 | C99: =N15*2 -> 23667.801 | E99: =B99/B98-1 -> -0.012761222 | F99: =C99/C98-1 -> 0.005365027 | N99: 14988.95
A100: 45545 | B100: 12263.4 | C100: =N16*2 -> 23850.801 | E100: =B100/B99-1 -> 0.0016989855 | F100: =C100/C99-1 -> 0.0077320238 | N100: 15177.95
A101: 45544 | B101: 12145.75 | C101: =N17*2 -> 23981.4 | E101: =B101/B100-1 -> -0.0095935874 | F101: =C101/C100-1 -> 0.0054756907 | N101: 15171.25
A102: 45541 | B102: 12186.15 | C102: =N18*2 -> 23998.1 | E102: =B102/B101-1 -> 0.0033262664 | F102: =C102/C101-1 -> 0.00069634049 | N102: 15176.4
A103: 45540 | B103: 12298.6 | C103: =N19*2 -> 23991.4 | E103: =B103/B102-1 -> 0.0092276888 | F103: =C103/C102-1 -> -0.00027915627 | N103: 15249.65
A104: 45539 | B104: 12336.25 | C104: =N20*2 -> 24078.1 | E104: =B104/B103-1 -> 0.0030613241 | F104: =C104/C103-1 -> 0.0036137624 | N104: 15245.75
A105: 45538 | B105: 12397.1 | C105: =N21*2 -> 23516.4 | E105: =B105/B104-1 -> 0.0049326173 | F105: =C105/C104-1 -> -0.023328221 | N105: 15399.2
... A118: 45518 | B118: 12205.65 | C118: =N34*2 -> 23826.699 | E118: =B118/B117-1 -> -0.00062636634 | F118: =C118/C117-1 -> 0.011504647 | N118: 15238.75
A119: 45517 | B119: 12176.25 | C119: =N4*2 -> 22734.5 | E119: =B119/B118-1 -> -0.0024087206 | F119: =C119/C118-1 -> -0.0458393 | N119: 15084.35
A120: 45516 | B120: 12273.25 | C120: =N5*2 -> 22529.1 | E120: =B120/B119-1 -> 0.0079663279 | F120: =C120/C119-1 -> -0.0090347441 | N120: 15096.85
A121: 45513 | B121: 12224.2 | C121: =N6*2 -> 22483.199 | E121: =B121/B120-1 -> -0.0039964964 | F121: =C121/C120-1 -> -0.0020373824 | N121: 15206
A122: 45512 | B122: 12218.85 | C122: =N7*2 -> 21844.5 | E122: =B122/B121-1 -> -0.00043765645 | F122: =C122/C121-1 -> -0.028407844 | N122: 15284.85
A123: 45511 | B123: 12371.5 | C123: =N8*2 -> 22352.6 | E123: =B123/B122-1 -> 0.012492992 | F123: =C123/C122-1 -> 0.023259842 | N123: 15140.15
A124: 45510 | B124: 12131.1 | C124: =N9*2 -> 22730.5 | E124: =B124/B123-1 -> -0.019431758 | F124: =C124/C123-1 -> 0.016906328 | N124: 15040.85
A125: 45509 | B125: 12200.85 | C125: =N10*2 -> 22707.301 | E125: =B125/B124-1 -> 0.0057496847 | F125: =C125/C124-1 -> -0.0010206207 | N125: 15033.3
A126: 45506 | B126: 12726.4 | C126: =N11*2 -> 22770.4 | E126: =B126/B125-1 -> 0.043074868 | F126: =C126/C125-1 -> 0.0027788247 | N126: 14828.85
A127: 45505 | B127: 13359.05 | C127: =N12*2 -> 23091.801 | E127: =B127/B126-1 -> 0.049711623 | F127: =C127/C126-1 -> 0.014114833 | N127: 14662.5
A128: 45504 | B128: 13115.8 | C128: =N13*2 -> 23251.199 | E128: =B128/B127-1 -> -0.01820863 | F128: =C128/C127-1 -> 0.0069028153 | N128: 14847.25
A129: 45503 | B129: 12873.65 | C129: =N14*2 -> 23541.5 | E129: =B129/B128-1 -> -0.018462465 | F129: =C129/C128-1 -> 0.012485411 | N129: 14859.7
A130: 45502 | B130: 12751.55 | C130: =N15*2 -> 23667.801 | E130: =B130/B129-1 -> -0.0094844896 | F130: =C130/C129-1 -> 0.005365027 | N130: 14952.1
... A143: 45482 | B143: 12827.7 | C143: =N28*2 -> 23685.4 | E143: =B143/B142-1 -> 0.0042981962 | F143: =C143/C142-1 -> -0.0136097 | N143: 14639.4
A144: 45481 | B144: 12023.6 | C144: =N24*2 -> 23953.699 | E144: =B144/B143-1 -> -0.062684659 | F144: =C144/C143-1 -> 0.011327604 | N144: 14719.25
...

Sheet FCFF
B2: Free Cashflow to Firm Calculation | C2: 2025 | D2: 2026 | E2: 2027 | F2: 2028 | G2: 2029 | H2: 2030 | I2: 2031 | J2: 2032 | K2: 2033 | L2: 2034 | M2: 2035 | N2: 2036 | O2: 2037 | P2: 2038 | Q2: 2039 | R2: 2040E
B3: EBIT | C3: ='Profit & Loss Statement'!J16 -> 26427 | D3: ='Profit & Loss Statement'!K16 -> 38055 | E3: ='Profit & Loss Statement'!L16 -> 51755 | F3: ='Profit & Loss Statement'!M16 -> 67281 | G3: ='Profit & Loss Statement'!N16 -> 84774
B5: EBIT(1-t) (or NOPAT) | C5: =C3*(1-$C$16) -> 19775.324 | D5: =D3*(1-$C$16) -> 28476.556 | E5: =E3*(1-$C$16) -> 38728.266 | F5: =F3*(1-$C$16) -> 50346.372 | G5: =G3*(1-$C$16) -> 63436.384
B6: Add Depreciation | C6: ='Profit & Loss Statement'!J11 -> 6453.3954 | D6: ='Profit & Loss Statement'!K11 -> 6977.0334 | E6: ='Profit & Loss Statement'!L11 -> 8146.8453 | F6: ='Profit & Loss Statement'!M11 -> 9146.126 | G6: ='Profit & Loss Statement'!N11 -> 10473.128
B7: Less Change in Net Working Capital | C7: =-Schedules_Populated!J22 -> 1217.3735 | D7: =-Schedules_Populated!K22 -> 573.95802 | E7: =-Schedules_Populated!L22 -> 56.371516 | F7: =-Schedules_Populated!M22 -> -151.08202 | G7: =-Schedules_Populated!N22 -> 253.61227
B8: Less Capital Expenditure | C8: =-Schedules_Populated!J106 -> -7884 | D8: =-Schedules_Populated!K106 -> -9680.0931 | E8: =-Schedules_Populated!L106 -> -10465.55 | F8: =-Schedules_Populated!M106 -> -12220.268 | G8: =-Schedules_Populated!N106 -> -13719.189
B9: FCFF | C9: =SUM(C5:C8) -> 19562.093 | D9: =SUM(D5:D8) -> 26347.455 | E9: =SUM(E5:E8) -> 36465.933 | F9: =SUM(F5:F8) -> 47121.148 | G9: =SUM(G5:G8) -> 60443.935 | H9: =G9*(1+H10) -> 80176.372 | I9: =H9*(1+I10) -> 104169.83 | J9: =I9*(1+J10) -> 132510.12 | K9: =J9*(1+K10) -> 164956.35 | L9: =K9*(1+L10) -> 200860.51 | M9: =L9*(1+M10) -> 239116.1 | N9: =M9*(1+N10) -> 278153.84 | O9: =N9*(1+O10) -> 315999.04 | ... Q9: =P9*(1+Q10) -> 379011.22 | R9: Terminal Growth Rate
B10: FCFF Growth | D10: =D9/C9-1 -> 0.34686277 | E10: =E9/D9-1 -> 0.38404007 | F10: =F9/E9-1 -> 0.29219642 | G10: =G9/F9-1 -> 0.28273477 | H10: =AVERAGE(D10:G10) -> 0.32645851 | I10: =H10-$I$11 -> 0.29925851 | J10: =I10-$I$11 -> 0.27205851 | K10: =J10-$I$11 -> 0.24485851 | L10: =K10-$I$11 -> 0.21765851 | M10: =L10-$I$11 -> 0.19045851 | N10: =M10-$I$11 -> 0.16325851 | O10: =N10-$I$11 -> 0.13605851 | P10: =O10-$I$11 -> 0.10885851 | ... R10: =Q10-$I$11 -> 0.054458508
I11: 0.0272
B13: Valuation Parameters
B14: Valuation as on Specified Date | C14: 45317
B15: Date of Year Ending | C15: 45747
B16: Tax Rate (Effective Future Rate) | C16: 0.2517
B17: WACC | C17: =WACC!I21 -> 0.069527936
B18: Terminal Growth Rate | C18: =WACC!M15 -> 0.0538
B20: Years | C20: =C2 -> 2025 | D20: =D2 -> 2026 | E20: =E2 -> 2027 | F20: =F2 -> 2028 | G20: =G2 -> 2029 | H20: =H2 -> 2030 | I20: =I2 -> 2031 | J20: =J2 -> 2032 | ... Q20: =Q2 -> 2039
B21: Time to Cashflow in Years | C21: =(C15-C14)/365 -> 1.1780822 | D21: =C21+1 -> 2.1780822 | E21: =D21+1 -> 3.1780822 | F21: =E21+1 -> 4.1780822 | G21: =F21+1 -> 5.1780822 | H21: =G21+1 -> 6.1780822 | I21: =H21+1 -> 7.1780822 | J21: =I21+1 -> 8.1780822 | K21: =J21+1 -> 9.1780822 | ... Q21: =P21+1 -> 15.178082
B22: FCFF | C22: =C9 -> 19562.093 | D22: =D9 -> 26347.455 | E22: =E9 -> 36465.933 | F22: =F9 -> 47121.148 | G22: =G9 -> 60443.935 | H22: =H9 -> 80176.372 | I22: =I9 -> 104169.83 | J22: =J9 -> 132510.12 | ... Q22: =Q9 -> 379011.22
B23: Discounted FCFF | C23: =C22/(1+$C$17)^C21 -> 18072.764 | D23: =D22/(1+$C$17)^D21 -> 22759.138 | E23: =E22/(1+$C$17)^E21 -> 29451.833 | F23: =F22/(1+$C$17)^F21 -> 35583.506 | G23: =G22/(1+$C$17)^G21 -> 42676.96 | H23: =H22/(1+$C$17)^H21 -> 52929.161 | I23: =I22/(1+$C$17)^I21 -> 64298.145 | J23: =J22/(1+$C$17)^J21 -> 76473.928 | ... Q23: =Q22/(1+$C$17)^Q21 -> 136637.99
Q24: =Q22*(1+C18)/(C17-C18) -> 25394434
B25: Terminal Value of FCFF | C25: =Q22*(1+C18)/(C17-C18) -> 25394434 | J25: Sensitivity Analysis
B26: NPV of Explicit Cash Flows | C26: =SUM(C23:Q23) -> 1170130.4
B27: NPV of Terminal Value | C27: =C25/(1+C17)^Q21 -> 9154991.5
B28: Enterprise Value | C28: =C26+C27 -> 10325122 | J28: =C34 -> 329192.55 | K28: =L28-0.5% -> 0.059527936 | L28: =M28-0.5% -> 0.064527936 | M28: =C17 -> 0.069527936 | N28: =M28+0.5% -> 0.074527936 | O28: =N28+0.5% -> 0.079527936
B29: Less Debt | C29: =-WACC!I15 -> -123.9 | J29: =J30-0.5% -> 0.0438 | K29: 374502.85 | L29: 567949.68 | M29: 567949.68 | N29: 374502.85 | O29: 214323.13
B30: Add Cash | C30: =CFS!B20 -> 24815.649 | J30: =J31-0.5% -> 0.0488 | K30: 293057.57 | L30: 399669.81 | M30: 399669.81 | N30: 293057.57 | O30: 184925.47
B31: No. of Shares Outstanding (in crores) | C31: =WACC!L3 -> 31.44 | J31: =C18 -> 0.0538 | K31: 293057.57 | L31: 399669.81 | M31: 399669.81 | N31: 293057.57 | O31: 184925.47
B32: Equity Value | C32: =C28+C29+C30 -> 10349814 | J32: =J31+0.5% -> 0.0588 | K32: 374502.85 | L32: 567949.68 | M32: 567949.68 | N32: 374502.85 | O32: 214323.13
B33: CMP | C33: =WACC!L2 -> 12310.65 | J33: =J32+0.5% -> 0.0638 | K33: 963962.16 | L33: 7839732.5 | M33: 7839732.5 | N33: 963962.16 | O33: 329192.55
B34: Value per Share (today) | C34: =C32/C31 -> 329192.55
B35: Upside/Downside | C35: =C34/C33-1 -> 25.740468
E38: Enterprise Value = Equity Value + Debt Value - Cash

Sheet Relative Valuation
C1: Numbers as of 26th January 2025*
C3: P/E Based Valuation | I3: Determine the peer set
C4: Peer Set | D4: P/E* | E4: Weighted Avg % (Assumed)
C5: Mahindra & Mahindra (M&M) | D5: 31.35 | E5: 0.4
C6: Hyundai Motor | D6: 22.9 | E6: 0.2
C7: Hindustan Motors | D7: 17.56 | E7: 0.4
M8: Total Earning of NTM | P8: ='Profit & Loss Statement'!K29*10 -> 261455.22
C9: Peer Average | D9: =SUMPRODUCT(D5:D7,E5:E7) -> 24.144 | M9: Total no of shares | P9: =WACC!L3 -> 31.44
C10: Maruti Suzuki: | H10: P/E | I10: 24.14 | M10: EPS for NTM of Maruti Suzuki | P10: =P8/P9 -> 8316.0058
C11: EPS NTM (Next Twelve Months) | D11: =P10 -> 8316.0058
C12: Target Share Price
C13: Maruti Suzuki Relative Price | D13: =D11*D9 -> 200781.64
C15: Model | D15: Price | E15: Weightages Assigned
C16: DCF suggested Price | D16: =FCFF!C34 -> 329192.55 | E16: 0.5
C17: Relative Suggested Price | D17: =D13 -> 200781.64 | E17: 0.5
C18: Blended Target Price | D18: =SUMPRODUCT(D16:D17,E16:E17) -> 264987.1
